{"nodes": [{"id": "c_users_maria_downloads_gpace_main_server_datastorage_js", "label": "dataStorage.js", "file_type": "code", "source_file": "C:\\Users\\maria\\Downloads\\GPAce-main\\server\\dataStorage.js", "source_location": "L1"}, {"id": "server_datastorage_datastorage", "label": "DataStorage", "file_type": "code", "source_file": "C:\\Users\\maria\\Downloads\\GPAce-main\\server\\dataStorage.js", "source_location": "L4"}, {"id": "server_datastorage_datastorage_constructor", "label": ".constructor()", "file_type": "code", "source_file": "C:\\Users\\maria\\Downloads\\GPAce-main\\server\\dataStorage.js", "source_location": "L5"}, {"id": "server_datastorage_datastorage_init", "label": ".init()", "file_type": "code", "source_file": "C:\\Users\\maria\\Downloads\\GPAce-main\\server\\dataStorage.js", "source_location": "L18"}, {"id": "server_datastorage_datastorage_iscachevalid", "label": "._isCacheValid()", "file_type": "code", "source_file": "C:\\Users\\maria\\Downloads\\GPAce-main\\server\\dataStorage.js", "source_location": "L43"}, {"id": "server_datastorage_datastorage_savetimetable", "label": ".saveTimetable()", "file_type": "code", "source_file": "C:\\Users\\maria\\Downloads\\GPAce-main\\server\\dataStorage.js", "source_location": "L49"}, {"id": "server_datastorage_datastorage_gettimetable", "label": ".getTimetable()", "file_type": "code", "source_file": "C:\\Users\\maria\\Downloads\\GPAce-main\\server\\dataStorage.js", "source_location": "L63"}, {"id": "server_datastorage_datastorage_cleartimetable", "label": ".clearTimetable()", "file_type": "code", "source_file": "C:\\Users\\maria\\Downloads\\GPAce-main\\server\\dataStorage.js", "source_location": "L87"}, {"id": "server_datastorage_datastorage_savelocation", "label": ".saveLocation()", "file_type": "code", "source_file": "C:\\Users\\maria\\Downloads\\GPAce-main\\server\\dataStorage.js", "source_location": "L102"}, {"id": "server_datastorage_datastorage_getlocations", "label": ".getLocations()", "file_type": "code", "source_file": "C:\\Users\\maria\\Downloads\\GPAce-main\\server\\dataStorage.js", "source_location": "L122"}, {"id": "server_datastorage_datastorage_saveschedule", "label": ".saveSchedule()", "file_type": "code", "source_file": "C:\\Users\\maria\\Downloads\\GPAce-main\\server\\dataStorage.js", "source_location": "L146"}, {"id": "server_datastorage_datastorage_getschedule", "label": ".getSchedule()", "file_type": "code", "source_file": "C:\\Users\\maria\\Downloads\\GPAce-main\\server\\dataStorage.js", "source_location": "L162"}], "edges": [{"source": "c_users_maria_downloads_gpace_main_server_datastorage_js", "target": "server_datastorage_datastorage", "relation": "contains", "confidence": "EXTRACTED", "source_file": "C:\\Users\\maria\\Downloads\\GPAce-main\\server\\dataStorage.js", "source_location": "L4", "weight": 1.0}, {"source": "server_datastorage_datastorage", "target": "server_datastorage_datastorage_constructor", "relation": "method", "confidence": "EXTRACTED", "source_file": "C:\\Users\\maria\\Downloads\\GPAce-main\\server\\dataStorage.js", "source_location": "L5", "weight": 1.0}, {"source": "server_datastorage_datastorage", "target": "server_datastorage_datastorage_init", "relation": "method", "confidence": "EXTRACTED", "source_file": "C:\\Users\\maria\\Downloads\\GPAce-main\\server\\dataStorage.js", "source_location": "L18", "weight": 1.0}, {"source": "server_datastorage_datastorage", "target": "server_datastorage_datastorage_iscachevalid", "relation": "method", "confidence": "EXTRACTED", "source_file": "C:\\Users\\maria\\Downloads\\GPAce-main\\server\\dataStorage.js", "source_location": "L43", "weight": 1.0}, {"source": "server_datastorage_datastorage", "target": "server_datastorage_datastorage_savetimetable", "relation": "method", "confidence": "EXTRACTED", "source_file": "C:\\Users\\maria\\Downloads\\GPAce-main\\server\\dataStorage.js", "source_location": "L49", "weight": 1.0}, {"source": "server_datastorage_datastorage", "target": "server_datastorage_datastorage_gettimetable", "relation": "method", "confidence": "EXTRACTED", "source_file": "C:\\Users\\maria\\Downloads\\GPAce-main\\server\\dataStorage.js", "source_location": "L63", "weight": 1.0}, {"source": "server_datastorage_datastorage", "target": "server_datastorage_datastorage_cleartimetable", "relation": "method", "confidence": "EXTRACTED", "source_file": "C:\\Users\\maria\\Downloads\\GPAce-main\\server\\dataStorage.js", "source_location": "L87", "weight": 1.0}, {"source": "server_datastorage_datastorage", "target": "server_datastorage_datastorage_savelocation", "relation": "method", "confidence": "EXTRACTED", "source_file": "C:\\Users\\maria\\Downloads\\GPAce-main\\server\\dataStorage.js", "source_location": "L102", "weight": 1.0}, {"source": "server_datastorage_datastorage", "target": "server_datastorage_datastorage_getlocations", "relation": "method", "confidence": "EXTRACTED", "source_file": "C:\\Users\\maria\\Downloads\\GPAce-main\\server\\dataStorage.js", "source_location": "L122", "weight": 1.0}, {"source": "server_datastorage_datastorage", "target": "server_datastorage_datastorage_saveschedule", "relation": "method", "confidence": "EXTRACTED", "source_file": "C:\\Users\\maria\\Downloads\\GPAce-main\\server\\dataStorage.js", "source_location": "L146", "weight": 1.0}, {"source": "server_datastorage_datastorage", "target": "server_datastorage_datastorage_getschedule", "relation": "method", "confidence": "EXTRACTED", "source_file": "C:\\Users\\maria\\Downloads\\GPAce-main\\server\\dataStorage.js", "source_location": "L162", "weight": 1.0}, {"source": "server_datastorage_datastorage_constructor", "target": "server_datastorage_datastorage_init", "relation": "calls", "confidence": "EXTRACTED", "source_file": "C:\\Users\\maria\\Downloads\\GPAce-main\\server\\dataStorage.js", "source_location": "L15", "weight": 1.0}, {"source": "server_datastorage_datastorage_gettimetable", "target": "server_datastorage_datastorage_iscachevalid", "relation": "calls", "confidence": "EXTRACTED", "source_file": "C:\\Users\\maria\\Downloads\\GPAce-main\\server\\dataStorage.js", "source_location": "L66", "weight": 1.0}, {"source": "server_datastorage_datastorage_savelocation", "target": "server_datastorage_datastorage_getlocations", "relation": "calls", "confidence": "EXTRACTED", "source_file": "C:\\Users\\maria\\Downloads\\GPAce-main\\server\\dataStorage.js", "source_location": "L105", "weight": 1.0}, {"source": "server_datastorage_datastorage_getlocations", "target": "server_datastorage_datastorage_iscachevalid", "relation": "calls", "confidence": "EXTRACTED", "source_file": "C:\\Users\\maria\\Downloads\\GPAce-main\\server\\dataStorage.js", "source_location": "L125", "weight": 1.0}, {"source": "server_datastorage_datastorage_getschedule", "target": "server_datastorage_datastorage_iscachevalid", "relation": "calls", "confidence": "EXTRACTED", "source_file": "C:\\Users\\maria\\Downloads\\GPAce-main\\server\\dataStorage.js", "source_location": "L165", "weight": 1.0}], "raw_calls": [{"caller_nid": "server_datastorage_datastorage_constructor", "callee": "join", "is_member_call": true, "source_file": "C:\\Users\\maria\\Downloads\\GPAce-main\\server\\dataStorage.js", "source_location": "L6"}, {"caller_nid": "server_datastorage_datastorage_init", "callee": "mkdir", "is_member_call": true, "source_file": "C:\\Users\\maria\\Downloads\\GPAce-main\\server\\dataStorage.js", "source_location": "L20"}, {"caller_nid": "server_datastorage_datastorage_init", "callee": "entries", "is_member_call": true, "source_file": "C:\\Users\\maria\\Downloads\\GPAce-main\\server\\dataStorage.js", "source_location": "L29"}, {"caller_nid": "server_datastorage_datastorage_init", "callee": "join", "is_member_call": true, "source_file": "C:\\Users\\maria\\Downloads\\GPAce-main\\server\\dataStorage.js", "source_location": "L30"}, {"caller_nid": "server_datastorage_datastorage_init", "callee": "access", "is_member_call": true, "source_file": "C:\\Users\\maria\\Downloads\\GPAce-main\\server\\dataStorage.js", "source_location": "L32"}, {"caller_nid": "server_datastorage_datastorage_init", "callee": "writeFile", "is_member_call": true, "source_file": "C:\\Users\\maria\\Downloads\\GPAce-main\\server\\dataStorage.js", "source_location": "L34"}, {"caller_nid": "server_datastorage_datastorage_init", "callee": "stringify", "is_member_call": true, "source_file": "C:\\Users\\maria\\Downloads\\GPAce-main\\server\\dataStorage.js", "source_location": "L34"}, {"caller_nid": "server_datastorage_datastorage_init", "callee": "error", "is_member_call": true, "source_file": "C:\\Users\\maria\\Downloads\\GPAce-main\\server\\dataStorage.js", "source_location": "L38"}, {"caller_nid": "server_datastorage_datastorage_iscachevalid", "callee": "now", "is_member_call": true, "source_file": "C:\\Users\\maria\\Downloads\\GPAce-main\\server\\dataStorage.js", "source_location": "L46"}, {"caller_nid": "server_datastorage_datastorage_savetimetable", "callee": "join", "is_member_call": true, "source_file": "C:\\Users\\maria\\Downloads\\GPAce-main\\server\\dataStorage.js", "source_location": "L51"}, {"caller_nid": "server_datastorage_datastorage_savetimetable", "callee": "writeFile", "is_member_call": true, "source_file": "C:\\Users\\maria\\Downloads\\GPAce-main\\server\\dataStorage.js", "source_location": "L52"}, {"caller_nid": "server_datastorage_datastorage_savetimetable", "callee": "stringify", "is_member_call": true, "source_file": "C:\\Users\\maria\\Downloads\\GPAce-main\\server\\dataStorage.js", "source_location": "L52"}, {"caller_nid": "server_datastorage_datastorage_savetimetable", "callee": "now", "is_member_call": true, "source_file": "C:\\Users\\maria\\Downloads\\GPAce-main\\server\\dataStorage.js", "source_location": "L55"}, {"caller_nid": "server_datastorage_datastorage_savetimetable", "callee": "error", "is_member_call": true, "source_file": "C:\\Users\\maria\\Downloads\\GPAce-main\\server\\dataStorage.js", "source_location": "L58"}, {"caller_nid": "server_datastorage_datastorage_gettimetable", "callee": "log", "is_member_call": true, "source_file": "C:\\Users\\maria\\Downloads\\GPAce-main\\server\\dataStorage.js", "source_location": "L67"}, {"caller_nid": "server_datastorage_datastorage_gettimetable", "callee": "log", "is_member_call": true, "source_file": "C:\\Users\\maria\\Downloads\\GPAce-main\\server\\dataStorage.js", "source_location": "L71"}, {"caller_nid": "server_datastorage_datastorage_gettimetable", "callee": "join", "is_member_call": true, "source_file": "C:\\Users\\maria\\Downloads\\GPAce-main\\server\\dataStorage.js", "source_location": "L72"}, {"caller_nid": "server_datastorage_datastorage_gettimetable", "callee": "readFile", "is_member_call": true, "source_file": "C:\\Users\\maria\\Downloads\\GPAce-main\\server\\dataStorage.js", "source_location": "L73"}, {"caller_nid": "server_datastorage_datastorage_gettimetable", "callee": "parse", "is_member_call": true, "source_file": "C:\\Users\\maria\\Downloads\\GPAce-main\\server\\dataStorage.js", "source_location": "L74"}, {"caller_nid": "server_datastorage_datastorage_gettimetable", "callee": "now", "is_member_call": true, "source_file": "C:\\Users\\maria\\Downloads\\GPAce-main\\server\\dataStorage.js", "source_location": "L78"}, {"caller_nid": "server_datastorage_datastorage_gettimetable", "callee": "error", "is_member_call": true, "source_file": "C:\\Users\\maria\\Downloads\\GPAce-main\\server\\dataStorage.js", "source_location": "L82"}, {"caller_nid": "server_datastorage_datastorage_cleartimetable", "callee": "join", "is_member_call": true, "source_file": "C:\\Users\\maria\\Downloads\\GPAce-main\\server\\dataStorage.js", "source_location": "L89"}, {"caller_nid": "server_datastorage_datastorage_cleartimetable", "callee": "writeFile", "is_member_call": true, "source_file": "C:\\Users\\maria\\Downloads\\GPAce-main\\server\\dataStorage.js", "source_location": "L90"}, {"caller_nid": "server_datastorage_datastorage_cleartimetable", "callee": "stringify", "is_member_call": true, "source_file": "C:\\Users\\maria\\Downloads\\GPAce-main\\server\\dataStorage.js", "source_location": "L90"}, {"caller_nid": "server_datastorage_datastorage_cleartimetable", "callee": "now", "is_member_call": true, "source_file": "C:\\Users\\maria\\Downloads\\GPAce-main\\server\\dataStorage.js", "source_location": "L93"}, {"caller_nid": "server_datastorage_datastorage_cleartimetable", "callee": "log", "is_member_call": true, "source_file": "C:\\Users\\maria\\Downloads\\GPAce-main\\server\\dataStorage.js", "source_location": "L94"}, {"caller_nid": "server_datastorage_datastorage_cleartimetable", "callee": "error", "is_member_call": true, "source_file": "C:\\Users\\maria\\Downloads\\GPAce-main\\server\\dataStorage.js", "source_location": "L97"}, {"caller_nid": "server_datastorage_datastorage_savelocation", "callee": "push", "is_member_call": true, "source_file": "C:\\Users\\maria\\Downloads\\GPAce-main\\server\\dataStorage.js", "source_location": "L106"}, {"caller_nid": "server_datastorage_datastorage_savelocation", "callee": "join", "is_member_call": true, "source_file": "C:\\Users\\maria\\Downloads\\GPAce-main\\server\\dataStorage.js", "source_location": "L108"}, {"caller_nid": "server_datastorage_datastorage_savelocation", "callee": "writeFile", "is_member_call": true, "source_file": "C:\\Users\\maria\\Downloads\\GPAce-main\\server\\dataStorage.js", "source_location": "L109"}, {"caller_nid": "server_datastorage_datastorage_savelocation", "callee": "stringify", "is_member_call": true, "source_file": "C:\\Users\\maria\\Downloads\\GPAce-main\\server\\dataStorage.js", "source_location": "L109"}, {"caller_nid": "server_datastorage_datastorage_savelocation", "callee": "now", "is_member_call": true, "source_file": "C:\\Users\\maria\\Downloads\\GPAce-main\\server\\dataStorage.js", "source_location": "L113"}, {"caller_nid": "server_datastorage_datastorage_savelocation", "callee": "error", "is_member_call": true, "source_file": "C:\\Users\\maria\\Downloads\\GPAce-main\\server\\dataStorage.js", "source_location": "L117"}, {"caller_nid": "server_datastorage_datastorage_getlocations", "callee": "log", "is_member_call": true, "source_file": "C:\\Users\\maria\\Downloads\\GPAce-main\\server\\dataStorage.js", "source_location": "L126"}, {"caller_nid": "server_datastorage_datastorage_getlocations", "callee": "log", "is_member_call": true, "source_file": "C:\\Users\\maria\\Downloads\\GPAce-main\\server\\dataStorage.js", "source_location": "L130"}, {"caller_nid": "server_datastorage_datastorage_getlocations", "callee": "join", "is_member_call": true, "source_file": "C:\\Users\\maria\\Downloads\\GPAce-main\\server\\dataStorage.js", "source_location": "L131"}, {"caller_nid": "server_datastorage_datastorage_getlocations", "callee": "readFile", "is_member_call": true, "source_file": "C:\\Users\\maria\\Downloads\\GPAce-main\\server\\dataStorage.js", "source_location": "L132"}, {"caller_nid": "server_datastorage_datastorage_getlocations", "callee": "parse", "is_member_call": true, "source_file": "C:\\Users\\maria\\Downloads\\GPAce-main\\server\\dataStorage.js", "source_location": "L133"}, {"caller_nid": "server_datastorage_datastorage_getlocations", "callee": "now", "is_member_call": true, "source_file": "C:\\Users\\maria\\Downloads\\GPAce-main\\server\\dataStorage.js", "source_location": "L137"}, {"caller_nid": "server_datastorage_datastorage_getlocations", "callee": "error", "is_member_call": true, "source_file": "C:\\Users\\maria\\Downloads\\GPAce-main\\server\\dataStorage.js", "source_location": "L141"}, {"caller_nid": "server_datastorage_datastorage_saveschedule", "callee": "join", "is_member_call": true, "source_file": "C:\\Users\\maria\\Downloads\\GPAce-main\\server\\dataStorage.js", "source_location": "L148"}, {"caller_nid": "server_datastorage_datastorage_saveschedule", "callee": "writeFile", "is_member_call": true, "source_file": "C:\\Users\\maria\\Downloads\\GPAce-main\\server\\dataStorage.js", "source_location": "L149"}, {"caller_nid": "server_datastorage_datastorage_saveschedule", "callee": "stringify", "is_member_call": true, "source_file": "C:\\Users\\maria\\Downloads\\GPAce-main\\server\\dataStorage.js", "source_location": "L149"}, {"caller_nid": "server_datastorage_datastorage_saveschedule", "callee": "now", "is_member_call": true, "source_file": "C:\\Users\\maria\\Downloads\\GPAce-main\\server\\dataStorage.js", "source_location": "L153"}, {"caller_nid": "server_datastorage_datastorage_saveschedule", "callee": "error", "is_member_call": true, "source_file": "C:\\Users\\maria\\Downloads\\GPAce-main\\server\\dataStorage.js", "source_location": "L157"}, {"caller_nid": "server_datastorage_datastorage_getschedule", "callee": "log", "is_member_call": true, "source_file": "C:\\Users\\maria\\Downloads\\GPAce-main\\server\\dataStorage.js", "source_location": "L166"}, {"caller_nid": "server_datastorage_datastorage_getschedule", "callee": "log", "is_member_call": true, "source_file": "C:\\Users\\maria\\Downloads\\GPAce-main\\server\\dataStorage.js", "source_location": "L170"}, {"caller_nid": "server_datastorage_datastorage_getschedule", "callee": "join", "is_member_call": true, "source_file": "C:\\Users\\maria\\Downloads\\GPAce-main\\server\\dataStorage.js", "source_location": "L171"}, {"caller_nid": "server_datastorage_datastorage_getschedule", "callee": "readFile", "is_member_call": true, "source_file": "C:\\Users\\maria\\Downloads\\GPAce-main\\server\\dataStorage.js", "source_location": "L172"}, {"caller_nid": "server_datastorage_datastorage_getschedule", "callee": "parse", "is_member_call": true, "source_file": "C:\\Users\\maria\\Downloads\\GPAce-main\\server\\dataStorage.js", "source_location": "L173"}, {"caller_nid": "server_datastorage_datastorage_getschedule", "callee": "now", "is_member_call": true, "source_file": "C:\\Users\\maria\\Downloads\\GPAce-main\\server\\dataStorage.js", "source_location": "L177"}, {"caller_nid": "server_datastorage_datastorage_getschedule", "callee": "error", "is_member_call": true, "source_file": "C:\\Users\\maria\\Downloads\\GPAce-main\\server\\dataStorage.js", "source_location": "L181"}]}