{"nodes": [{"id": "c_users_maria_downloads_gpace_main_js_semester_management_js", "label": "semester-management.js", "file_type": "code", "source_file": "C:\\Users\\maria\\Downloads\\GPAce-main\\js\\semester-management.js", "source_location": "L1"}, {"id": "js_semester_management_getcurrentsemester", "label": "getCurrentSemester()", "file_type": "code", "source_file": "C:\\Users\\maria\\Downloads\\GPAce-main\\js\\semester-management.js", "source_location": "L16"}, {"id": "js_semester_management_setcurrentsemester", "label": "setCurrentSemester()", "file_type": "code", "source_file": "C:\\Users\\maria\\Downloads\\GPAce-main\\js\\semester-management.js", "source_location": "L17"}, {"id": "js_semester_management_updatesemesterselector", "label": "updateSemesterSelector()", "file_type": "code", "source_file": "C:\\Users\\maria\\Downloads\\GPAce-main\\js\\semester-management.js", "source_location": "L22"}, {"id": "js_semester_management_handlesemesterchange", "label": "handleSemesterChange()", "file_type": "code", "source_file": "C:\\Users\\maria\\Downloads\\GPAce-main\\js\\semester-management.js", "source_location": "L276"}, {"id": "js_semester_management_initsemestermanagement", "label": "initSemesterManagement()", "file_type": "code", "source_file": "C:\\Users\\maria\\Downloads\\GPAce-main\\js\\semester-management.js", "source_location": "L312"}, {"id": "js_semester_management_waitforauth", "label": "waitForAuth()", "file_type": "code", "source_file": "C:\\Users\\maria\\Downloads\\GPAce-main\\js\\semester-management.js", "source_location": "L365"}, {"id": "js_semester_management_logsemesterdebuginfo", "label": "logSemesterDebugInfo()", "file_type": "code", "source_file": "C:\\Users\\maria\\Downloads\\GPAce-main\\js\\semester-management.js", "source_location": "L394"}, {"id": "js_semester_management_migratetosemestersystem", "label": "migrateToSemesterSystem()", "file_type": "code", "source_file": "C:\\Users\\maria\\Downloads\\GPAce-main\\js\\semester-management.js", "source_location": "L418"}, {"id": "js_semester_management_showcopysemestermodal", "label": "showCopySemesterModal()", "file_type": "code", "source_file": "C:\\Users\\maria\\Downloads\\GPAce-main\\js\\semester-management.js", "source_location": "L460"}, {"id": "js_semester_management_copysubjectstonewsemester", "label": "copySubjectsToNewSemester()", "file_type": "code", "source_file": "C:\\Users\\maria\\Downloads\\GPAce-main\\js\\semester-management.js", "source_location": "L496"}, {"id": "js_semester_management_shownewsemestermodal", "label": "showNewSemesterModal()", "file_type": "code", "source_file": "C:\\Users\\maria\\Downloads\\GPAce-main\\js\\semester-management.js", "source_location": "L578"}, {"id": "js_semester_management_createnewsemester", "label": "createNewSemester()", "file_type": "code", "source_file": "C:\\Users\\maria\\Downloads\\GPAce-main\\js\\semester-management.js", "source_location": "L600"}, {"id": "js_semester_management_setupsemestertemplatebuttons", "label": "setupSemesterTemplateButtons()", "file_type": "code", "source_file": "C:\\Users\\maria\\Downloads\\GPAce-main\\js\\semester-management.js", "source_location": "L711"}, {"id": "js_semester_management_updatesemesterpreview", "label": "updateSemesterPreview()", "file_type": "code", "source_file": "C:\\Users\\maria\\Downloads\\GPAce-main\\js\\semester-management.js", "source_location": "L736"}, {"id": "js_semester_management_selectcolortag", "label": "selectColorTag()", "file_type": "code", "source_file": "C:\\Users\\maria\\Downloads\\GPAce-main\\js\\semester-management.js", "source_location": "L773"}, {"id": "js_semester_management_editsemesterdetails", "label": "editSemesterDetails()", "file_type": "code", "source_file": "C:\\Users\\maria\\Downloads\\GPAce-main\\js\\semester-management.js", "source_location": "L792"}, {"id": "js_semester_management_savesemesterdetails", "label": "saveSemesterDetails()", "file_type": "code", "source_file": "C:\\Users\\maria\\Downloads\\GPAce-main\\js\\semester-management.js", "source_location": "L848"}, {"id": "js_semester_management_archivesemester", "label": "archiveSemester()", "file_type": "code", "source_file": "C:\\Users\\maria\\Downloads\\GPAce-main\\js\\semester-management.js", "source_location": "L966"}, {"id": "js_semester_management_confirmarchivesemester", "label": "confirmArchiveSemester()", "file_type": "code", "source_file": "C:\\Users\\maria\\Downloads\\GPAce-main\\js\\semester-management.js", "source_location": "L989"}, {"id": "js_semester_management_deletesemester", "label": "deleteSemester()", "file_type": "code", "source_file": "C:\\Users\\maria\\Downloads\\GPAce-main\\js\\semester-management.js", "source_location": "L1079"}, {"id": "js_semester_management_confirmdeletesemester", "label": "confirmDeleteSemester()", "file_type": "code", "source_file": "C:\\Users\\maria\\Downloads\\GPAce-main\\js\\semester-management.js", "source_location": "L1128"}, {"id": "js_semester_management_forcesyncsemester", "label": "forceSyncSemester()", "file_type": "code", "source_file": "C:\\Users\\maria\\Downloads\\GPAce-main\\js\\semester-management.js", "source_location": "L1212"}, {"id": "js_semester_management_updatesyncstatus", "label": "updateSyncStatus()", "file_type": "code", "source_file": "C:\\Users\\maria\\Downloads\\GPAce-main\\js\\semester-management.js", "source_location": "L1267"}, {"id": "js_semester_management_updatestorageusage", "label": "updateStorageUsage()", "file_type": "code", "source_file": "C:\\Users\\maria\\Downloads\\GPAce-main\\js\\semester-management.js", "source_location": "L1328"}, {"id": "js_semester_management_showstoragemanager", "label": "showStorageManager()", "file_type": "code", "source_file": "C:\\Users\\maria\\Downloads\\GPAce-main\\js\\semester-management.js", "source_location": "L1388"}], "edges": [{"source": "c_users_maria_downloads_gpace_main_js_semester_management_js", "target": "c_users_maria_downloads_gpace_main_services_storageservice_ts", "relation": "imports_from", "confidence": "EXTRACTED", "source_file": "C:\\Users\\maria\\Downloads\\GPAce-main\\js\\semester-management.js", "source_location": "L11", "weight": 1.0}, {"source": "c_users_maria_downloads_gpace_main_js_semester_management_js", "target": "c_users_maria_downloads_gpace_main_js_services_semesterservice_ts", "relation": "imports_from", "confidence": "EXTRACTED", "source_file": "C:\\Users\\maria\\Downloads\\GPAce-main\\js\\semester-management.js", "source_location": "L12", "weight": 1.0}, {"source": "c_users_maria_downloads_gpace_main_js_semester_management_js", "target": "c_users_maria_downloads_gpace_main_js_services_toastservice_ts", "relation": "imports_from", "confidence": "EXTRACTED", "source_file": "C:\\Users\\maria\\Downloads\\GPAce-main\\js\\semester-management.js", "source_location": "L13", "weight": 1.0}, {"source": "c_users_maria_downloads_gpace_main_js_semester_management_js", "target": "js_semester_management_getcurrentsemester", "relation": "contains", "confidence": "EXTRACTED", "source_file": "C:\\Users\\maria\\Downloads\\GPAce-main\\js\\semester-management.js", "source_location": "L16", "weight": 1.0}, {"source": "c_users_maria_downloads_gpace_main_js_semester_management_js", "target": "js_semester_management_setcurrentsemester", "relation": "contains", "confidence": "EXTRACTED", "source_file": "C:\\Users\\maria\\Downloads\\GPAce-main\\js\\semester-management.js", "source_location": "L17", "weight": 1.0}, {"source": "c_users_maria_downloads_gpace_main_js_semester_management_js", "target": "js_semester_management_updatesemesterselector", "relation": "contains", "confidence": "EXTRACTED", "source_file": "C:\\Users\\maria\\Downloads\\GPAce-main\\js\\semester-management.js", "source_location": "L22", "weight": 1.0}, {"source": "c_users_maria_downloads_gpace_main_js_semester_management_js", "target": "js_semester_management_handlesemesterchange", "relation": "contains", "confidence": "EXTRACTED", "source_file": "C:\\Users\\maria\\Downloads\\GPAce-main\\js\\semester-management.js", "source_location": "L276", "weight": 1.0}, {"source": "c_users_maria_downloads_gpace_main_js_semester_management_js", "target": "js_semester_management_initsemestermanagement", "relation": "contains", "confidence": "EXTRACTED", "source_file": "C:\\Users\\maria\\Downloads\\GPAce-main\\js\\semester-management.js", "source_location": "L312", "weight": 1.0}, {"source": "c_users_maria_downloads_gpace_main_js_semester_management_js", "target": "js_semester_management_waitforauth", "relation": "contains", "confidence": "EXTRACTED", "source_file": "C:\\Users\\maria\\Downloads\\GPAce-main\\js\\semester-management.js", "source_location": "L365", "weight": 1.0}, {"source": "c_users_maria_downloads_gpace_main_js_semester_management_js", "target": "js_semester_management_logsemesterdebuginfo", "relation": "contains", "confidence": "EXTRACTED", "source_file": "C:\\Users\\maria\\Downloads\\GPAce-main\\js\\semester-management.js", "source_location": "L394", "weight": 1.0}, {"source": "c_users_maria_downloads_gpace_main_js_semester_management_js", "target": "js_semester_management_migratetosemestersystem", "relation": "contains", "confidence": "EXTRACTED", "source_file": "C:\\Users\\maria\\Downloads\\GPAce-main\\js\\semester-management.js", "source_location": "L418", "weight": 1.0}, {"source": "c_users_maria_downloads_gpace_main_js_semester_management_js", "target": "js_semester_management_showcopysemestermodal", "relation": "contains", "confidence": "EXTRACTED", "source_file": "C:\\Users\\maria\\Downloads\\GPAce-main\\js\\semester-management.js", "source_location": "L460", "weight": 1.0}, {"source": "c_users_maria_downloads_gpace_main_js_semester_management_js", "target": "js_semester_management_copysubjectstonewsemester", "relation": "contains", "confidence": "EXTRACTED", "source_file": "C:\\Users\\maria\\Downloads\\GPAce-main\\js\\semester-management.js", "source_location": "L496", "weight": 1.0}, {"source": "c_users_maria_downloads_gpace_main_js_semester_management_js", "target": "js_semester_management_shownewsemestermodal", "relation": "contains", "confidence": "EXTRACTED", "source_file": "C:\\Users\\maria\\Downloads\\GPAce-main\\js\\semester-management.js", "source_location": "L578", "weight": 1.0}, {"source": "c_users_maria_downloads_gpace_main_js_semester_management_js", "target": "js_semester_management_createnewsemester", "relation": "contains", "confidence": "EXTRACTED", "source_file": "C:\\Users\\maria\\Downloads\\GPAce-main\\js\\semester-management.js", "source_location": "L600", "weight": 1.0}, {"source": "c_users_maria_downloads_gpace_main_js_semester_management_js", "target": "js_semester_management_setupsemestertemplatebuttons", "relation": "contains", "confidence": "EXTRACTED", "source_file": "C:\\Users\\maria\\Downloads\\GPAce-main\\js\\semester-management.js", "source_location": "L711", "weight": 1.0}, {"source": "c_users_maria_downloads_gpace_main_js_semester_management_js", "target": "js_semester_management_updatesemesterpreview", "relation": "contains", "confidence": "EXTRACTED", "source_file": "C:\\Users\\maria\\Downloads\\GPAce-main\\js\\semester-management.js", "source_location": "L736", "weight": 1.0}, {"source": "c_users_maria_downloads_gpace_main_js_semester_management_js", "target": "js_semester_management_selectcolortag", "relation": "contains", "confidence": "EXTRACTED", "source_file": "C:\\Users\\maria\\Downloads\\GPAce-main\\js\\semester-management.js", "source_location": "L773", "weight": 1.0}, {"source": "c_users_maria_downloads_gpace_main_js_semester_management_js", "target": "js_semester_management_editsemesterdetails", "relation": "contains", "confidence": "EXTRACTED", "source_file": "C:\\Users\\maria\\Downloads\\GPAce-main\\js\\semester-management.js", "source_location": "L792", "weight": 1.0}, {"source": "c_users_maria_downloads_gpace_main_js_semester_management_js", "target": "js_semester_management_savesemesterdetails", "relation": "contains", "confidence": "EXTRACTED", "source_file": "C:\\Users\\maria\\Downloads\\GPAce-main\\js\\semester-management.js", "source_location": "L848", "weight": 1.0}, {"source": "c_users_maria_downloads_gpace_main_js_semester_management_js", "target": "js_semester_management_archivesemester", "relation": "contains", "confidence": "EXTRACTED", "source_file": "C:\\Users\\maria\\Downloads\\GPAce-main\\js\\semester-management.js", "source_location": "L966", "weight": 1.0}, {"source": "c_users_maria_downloads_gpace_main_js_semester_management_js", "target": "js_semester_management_confirmarchivesemester", "relation": "contains", "confidence": "EXTRACTED", "source_file": "C:\\Users\\maria\\Downloads\\GPAce-main\\js\\semester-management.js", "source_location": "L989", "weight": 1.0}, {"source": "c_users_maria_downloads_gpace_main_js_semester_management_js", "target": "js_semester_management_deletesemester", "relation": "contains", "confidence": "EXTRACTED", "source_file": "C:\\Users\\maria\\Downloads\\GPAce-main\\js\\semester-management.js", "source_location": "L1079", "weight": 1.0}, {"source": "c_users_maria_downloads_gpace_main_js_semester_management_js", "target": "js_semester_management_confirmdeletesemester", "relation": "contains", "confidence": "EXTRACTED", "source_file": "C:\\Users\\maria\\Downloads\\GPAce-main\\js\\semester-management.js", "source_location": "L1128", "weight": 1.0}, {"source": "c_users_maria_downloads_gpace_main_js_semester_management_js", "target": "js_semester_management_forcesyncsemester", "relation": "contains", "confidence": "EXTRACTED", "source_file": "C:\\Users\\maria\\Downloads\\GPAce-main\\js\\semester-management.js", "source_location": "L1212", "weight": 1.0}, {"source": "c_users_maria_downloads_gpace_main_js_semester_management_js", "target": "js_semester_management_updatesyncstatus", "relation": "contains", "confidence": "EXTRACTED", "source_file": "C:\\Users\\maria\\Downloads\\GPAce-main\\js\\semester-management.js", "source_location": "L1267", "weight": 1.0}, {"source": "c_users_maria_downloads_gpace_main_js_semester_management_js", "target": "js_semester_management_updatestorageusage", "relation": "contains", "confidence": "EXTRACTED", "source_file": "C:\\Users\\maria\\Downloads\\GPAce-main\\js\\semester-management.js", "source_location": "L1328", "weight": 1.0}, {"source": "c_users_maria_downloads_gpace_main_js_semester_management_js", "target": "js_semester_management_showstoragemanager", "relation": "contains", "confidence": "EXTRACTED", "source_file": "C:\\Users\\maria\\Downloads\\GPAce-main\\js\\semester-management.js", "source_location": "L1388", "weight": 1.0}, {"source": "js_semester_management_updatesemesterselector", "target": "js_semester_management_getcurrentsemester", "relation": "calls", "confidence": "EXTRACTED", "source_file": "C:\\Users\\maria\\Downloads\\GPAce-main\\js\\semester-management.js", "source_location": "L197", "weight": 1.0}, {"source": "js_semester_management_updatesemesterselector", "target": "js_semester_management_setcurrentsemester", "relation": "calls", "confidence": "EXTRACTED", "source_file": "C:\\Users\\maria\\Downloads\\GPAce-main\\js\\semester-management.js", "source_location": "L209", "weight": 1.0}, {"source": "js_semester_management_updatesemesterselector", "target": "js_semester_management_updatesyncstatus", "relation": "calls", "confidence": "EXTRACTED", "source_file": "C:\\Users\\maria\\Downloads\\GPAce-main\\js\\semester-management.js", "source_location": "L263", "weight": 1.0}, {"source": "js_semester_management_updatesemesterselector", "target": "js_semester_management_updatestorageusage", "relation": "calls", "confidence": "EXTRACTED", "source_file": "C:\\Users\\maria\\Downloads\\GPAce-main\\js\\semester-management.js", "source_location": "L266", "weight": 1.0}, {"source": "js_semester_management_handlesemesterchange", "target": "js_semester_management_shownewsemestermodal", "relation": "calls", "confidence": "EXTRACTED", "source_file": "C:\\Users\\maria\\Downloads\\GPAce-main\\js\\semester-management.js", "source_location": "L282", "weight": 1.0}, {"source": "js_semester_management_handlesemesterchange", "target": "js_semester_management_getcurrentsemester", "relation": "calls", "confidence": "EXTRACTED", "source_file": "C:\\Users\\maria\\Downloads\\GPAce-main\\js\\semester-management.js", "source_location": "L285", "weight": 1.0}, {"source": "js_semester_management_handlesemesterchange", "target": "js_semester_management_setcurrentsemester", "relation": "calls", "confidence": "EXTRACTED", "source_file": "C:\\Users\\maria\\Downloads\\GPAce-main\\js\\semester-management.js", "source_location": "L292", "weight": 1.0}, {"source": "js_semester_management_initsemestermanagement", "target": "js_semester_management_logsemesterdebuginfo", "relation": "calls", "confidence": "EXTRACTED", "source_file": "C:\\Users\\maria\\Downloads\\GPAce-main\\js\\semester-management.js", "source_location": "L319", "weight": 1.0}, {"source": "js_semester_management_initsemestermanagement", "target": "js_semester_management_waitforauth", "relation": "calls", "confidence": "EXTRACTED", "source_file": "C:\\Users\\maria\\Downloads\\GPAce-main\\js\\semester-management.js", "source_location": "L322", "weight": 1.0}, {"source": "js_semester_management_initsemestermanagement", "target": "js_semester_management_updatesemesterselector", "relation": "calls", "confidence": "EXTRACTED", "source_file": "C:\\Users\\maria\\Downloads\\GPAce-main\\js\\semester-management.js", "source_location": "L339", "weight": 1.0}, {"source": "js_semester_management_initsemestermanagement", "target": "js_semester_management_setupsemestertemplatebuttons", "relation": "calls", "confidence": "EXTRACTED", "source_file": "C:\\Users\\maria\\Downloads\\GPAce-main\\js\\semester-management.js", "source_location": "L344", "weight": 1.0}, {"source": "js_semester_management_initsemestermanagement", "target": "js_semester_management_migratetosemestersystem", "relation": "calls", "confidence": "EXTRACTED", "source_file": "C:\\Users\\maria\\Downloads\\GPAce-main\\js\\semester-management.js", "source_location": "L348", "weight": 1.0}, {"source": "js_semester_management_initsemestermanagement", "target": "js_semester_management_updatestorageusage", "relation": "calls", "confidence": "EXTRACTED", "source_file": "C:\\Users\\maria\\Downloads\\GPAce-main\\js\\semester-management.js", "source_location": "L351", "weight": 1.0}, {"source": "js_semester_management_showcopysemestermodal", "target": "js_semester_management_getcurrentsemester", "relation": "calls", "confidence": "EXTRACTED", "source_file": "C:\\Users\\maria\\Downloads\\GPAce-main\\js\\semester-management.js", "source_location": "L479", "weight": 1.0}, {"source": "js_semester_management_copysubjectstonewsemester", "target": "js_semester_management_setcurrentsemester", "relation": "calls", "confidence": "EXTRACTED", "source_file": "C:\\Users\\maria\\Downloads\\GPAce-main\\js\\semester-management.js", "source_location": "L542", "weight": 1.0}, {"source": "js_semester_management_copysubjectstonewsemester", "target": "js_semester_management_updatesemesterselector", "relation": "calls", "confidence": "EXTRACTED", "source_file": "C:\\Users\\maria\\Downloads\\GPAce-main\\js\\semester-management.js", "source_location": "L564", "weight": 1.0}, {"source": "js_semester_management_shownewsemestermodal", "target": "js_semester_management_setupsemestertemplatebuttons", "relation": "calls", "confidence": "EXTRACTED", "source_file": "C:\\Users\\maria\\Downloads\\GPAce-main\\js\\semester-management.js", "source_location": "L590", "weight": 1.0}, {"source": "js_semester_management_createnewsemester", "target": "js_semester_management_setcurrentsemester", "relation": "calls", "confidence": "EXTRACTED", "source_file": "C:\\Users\\maria\\Downloads\\GPAce-main\\js\\semester-management.js", "source_location": "L660", "weight": 1.0}, {"source": "js_semester_management_selectcolortag", "target": "js_semester_management_updatesemesterpreview", "relation": "calls", "confidence": "EXTRACTED", "source_file": "C:\\Users\\maria\\Downloads\\GPAce-main\\js\\semester-management.js", "source_location": "L786", "weight": 1.0}, {"source": "js_semester_management_editsemesterdetails", "target": "js_semester_management_setupsemestertemplatebuttons", "relation": "calls", "confidence": "EXTRACTED", "source_file": "C:\\Users\\maria\\Downloads\\GPAce-main\\js\\semester-management.js", "source_location": "L830", "weight": 1.0}, {"source": "js_semester_management_editsemesterdetails", "target": "js_semester_management_updatesemesterpreview", "relation": "calls", "confidence": "EXTRACTED", "source_file": "C:\\Users\\maria\\Downloads\\GPAce-main\\js\\semester-management.js", "source_location": "L833", "weight": 1.0}, {"source": "js_semester_management_savesemesterdetails", "target": "js_semester_management_updatesemesterselector", "relation": "calls", "confidence": "EXTRACTED", "source_file": "C:\\Users\\maria\\Downloads\\GPAce-main\\js\\semester-management.js", "source_location": "L924", "weight": 1.0}, {"source": "js_semester_management_archivesemester", "target": "js_semester_management_getcurrentsemester", "relation": "calls", "confidence": "EXTRACTED", "source_file": "C:\\Users\\maria\\Downloads\\GPAce-main\\js\\semester-management.js", "source_location": "L967", "weight": 1.0}, {"source": "js_semester_management_archivesemester", "target": "js_semester_management_confirmarchivesemester", "relation": "calls", "confidence": "EXTRACTED", "source_file": "C:\\Users\\maria\\Downloads\\GPAce-main\\js\\semester-management.js", "source_location": "L978", "weight": 1.0}, {"source": "js_semester_management_confirmarchivesemester", "target": "js_semester_management_getcurrentsemester", "relation": "calls", "confidence": "EXTRACTED", "source_file": "C:\\Users\\maria\\Downloads\\GPAce-main\\js\\semester-management.js", "source_location": "L1000", "weight": 1.0}, {"source": "js_semester_management_confirmarchivesemester", "target": "js_semester_management_setcurrentsemester", "relation": "calls", "confidence": "EXTRACTED", "source_file": "C:\\Users\\maria\\Downloads\\GPAce-main\\js\\semester-management.js", "source_location": "L1030", "weight": 1.0}, {"source": "js_semester_management_confirmarchivesemester", "target": "js_semester_management_updatesemesterselector", "relation": "calls", "confidence": "EXTRACTED", "source_file": "C:\\Users\\maria\\Downloads\\GPAce-main\\js\\semester-management.js", "source_location": "L1036", "weight": 1.0}, {"source": "js_semester_management_deletesemester", "target": "js_semester_management_getcurrentsemester", "relation": "calls", "confidence": "EXTRACTED", "source_file": "C:\\Users\\maria\\Downloads\\GPAce-main\\js\\semester-management.js", "source_location": "L1080", "weight": 1.0}, {"source": "js_semester_management_deletesemester", "target": "js_semester_management_confirmdeletesemester", "relation": "calls", "confidence": "EXTRACTED", "source_file": "C:\\Users\\maria\\Downloads\\GPAce-main\\js\\semester-management.js", "source_location": "L1116", "weight": 1.0}, {"source": "js_semester_management_confirmdeletesemester", "target": "js_semester_management_getcurrentsemester", "relation": "calls", "confidence": "EXTRACTED", "source_file": "C:\\Users\\maria\\Downloads\\GPAce-main\\js\\semester-management.js", "source_location": "L1137", "weight": 1.0}, {"source": "js_semester_management_confirmdeletesemester", "target": "js_semester_management_setcurrentsemester", "relation": "calls", "confidence": "EXTRACTED", "source_file": "C:\\Users\\maria\\Downloads\\GPAce-main\\js\\semester-management.js", "source_location": "L1150", "weight": 1.0}, {"source": "js_semester_management_confirmdeletesemester", "target": "js_semester_management_updatesemesterselector", "relation": "calls", "confidence": "EXTRACTED", "source_file": "C:\\Users\\maria\\Downloads\\GPAce-main\\js\\semester-management.js", "source_location": "L1169", "weight": 1.0}, {"source": "js_semester_management_updatesyncstatus", "target": "js_semester_management_getcurrentsemester", "relation": "calls", "confidence": "EXTRACTED", "source_file": "C:\\Users\\maria\\Downloads\\GPAce-main\\js\\semester-management.js", "source_location": "L1282", "weight": 1.0}], "raw_calls": [{"caller_nid": "js_semester_management_updatesemesterselector", "callee": "getStorage", "is_member_call": false, "source_file": "C:\\Users\\maria\\Downloads\\GPAce-main\\js\\semester-management.js", "source_location": "L23"}, {"caller_nid": "js_semester_management_updatesemesterselector", "callee": "get", "is_member_call": true, "source_file": "C:\\Users\\maria\\Downloads\\GPAce-main\\js\\semester-management.js", "source_location": "L26"}, {"caller_nid": "js_semester_management_updatesemesterselector", "callee": "getElementById", "is_member_call": true, "source_file": "C:\\Users\\maria\\Downloads\\GPAce-main\\js\\semester-management.js", "source_location": "L27"}, {"caller_nid": "js_semester_management_updatesemesterselector", "callee": "getElementById", "is_member_call": true, "source_file": "C:\\Users\\maria\\Downloads\\GPAce-main\\js\\semester-management.js", "source_location": "L28"}, {"caller_nid": "js_semester_management_updatesemesterselector", "callee": "import", "is_member_call": false, "source_file": "C:\\Users\\maria\\Downloads\\GPAce-main\\js\\semester-management.js", "source_location": "L41"}, {"caller_nid": "js_semester_management_updatesemesterselector", "callee": "listUserSemesters", "is_member_call": false, "source_file": "C:\\Users\\maria\\Downloads\\GPAce-main\\js\\semester-management.js", "source_location": "L42"}, {"caller_nid": "js_semester_management_updatesemesterselector", "callee": "forEach", "is_member_call": true, "source_file": "C:\\Users\\maria\\Downloads\\GPAce-main\\js\\semester-management.js", "source_location": "L45"}, {"caller_nid": "js_semester_management_updatesemesterselector", "callee": "set", "is_member_call": true, "source_file": "C:\\Users\\maria\\Downloads\\GPAce-main\\js\\semester-management.js", "source_location": "L61"}, {"caller_nid": "js_semester_management_updatesemesterselector", "callee": "log", "is_member_call": true, "source_file": "C:\\Users\\maria\\Downloads\\GPAce-main\\js\\semester-management.js", "source_location": "L63"}, {"caller_nid": "js_semester_management_updatesemesterselector", "callee": "warn", "is_member_call": true, "source_file": "C:\\Users\\maria\\Downloads\\GPAce-main\\js\\semester-management.js", "source_location": "L65"}, {"caller_nid": "js_semester_management_updatesemesterselector", "callee": "sort", "is_member_call": true, "source_file": "C:\\Users\\maria\\Downloads\\GPAce-main\\js\\semester-management.js", "source_location": "L71"}, {"caller_nid": "js_semester_management_updatesemesterselector", "callee": "filter", "is_member_call": true, "source_file": "C:\\Users\\maria\\Downloads\\GPAce-main\\js\\semester-management.js", "source_location": "L71"}, {"caller_nid": "js_semester_management_updatesemesterselector", "callee": "entries", "is_member_call": true, "source_file": "C:\\Users\\maria\\Downloads\\GPAce-main\\js\\semester-management.js", "source_location": "L71"}, {"caller_nid": "js_semester_management_updatesemesterselector", "callee": "forEach", "is_member_call": true, "source_file": "C:\\Users\\maria\\Downloads\\GPAce-main\\js\\semester-management.js", "source_location": "L92"}, {"caller_nid": "js_semester_management_updatesemesterselector", "callee": "createElement", "is_member_call": true, "source_file": "C:\\Users\\maria\\Downloads\\GPAce-main\\js\\semester-management.js", "source_location": "L103"}, {"caller_nid": "js_semester_management_updatesemesterselector", "callee": "appendChild", "is_member_call": true, "source_file": "C:\\Users\\maria\\Downloads\\GPAce-main\\js\\semester-management.js", "source_location": "L105"}, {"caller_nid": "js_semester_management_updatesemesterselector", "callee": "forEach", "is_member_call": true, "source_file": "C:\\Users\\maria\\Downloads\\GPAce-main\\js\\semester-management.js", "source_location": "L108"}, {"caller_nid": "js_semester_management_updatesemesterselector", "callee": "createElement", "is_member_call": true, "source_file": "C:\\Users\\maria\\Downloads\\GPAce-main\\js\\semester-management.js", "source_location": "L150"}, {"caller_nid": "js_semester_management_updatesemesterselector", "callee": "appendChild", "is_member_call": true, "source_file": "C:\\Users\\maria\\Downloads\\GPAce-main\\js\\semester-management.js", "source_location": "L152"}, {"caller_nid": "js_semester_management_updatesemesterselector", "callee": "forEach", "is_member_call": true, "source_file": "C:\\Users\\maria\\Downloads\\GPAce-main\\js\\semester-management.js", "source_location": "L155"}, {"caller_nid": "js_semester_management_updatesemesterselector", "callee": "createElement", "is_member_call": true, "source_file": "C:\\Users\\maria\\Downloads\\GPAce-main\\js\\semester-management.js", "source_location": "L184"}, {"caller_nid": "js_semester_management_updatesemesterselector", "callee": "appendChild", "is_member_call": true, "source_file": "C:\\Users\\maria\\Downloads\\GPAce-main\\js\\semester-management.js", "source_location": "L187"}, {"caller_nid": "js_semester_management_updatesemesterselector", "callee": "createElement", "is_member_call": true, "source_file": "C:\\Users\\maria\\Downloads\\GPAce-main\\js\\semester-management.js", "source_location": "L190"}, {"caller_nid": "js_semester_management_updatesemesterselector", "callee": "appendChild", "is_member_call": true, "source_file": "C:\\Users\\maria\\Downloads\\GPAce-main\\js\\semester-management.js", "source_location": "L194"}, {"caller_nid": "js_semester_management_updatesemesterselector", "callee": "includes", "is_member_call": true, "source_file": "C:\\Users\\maria\\Downloads\\GPAce-main\\js\\semester-management.js", "source_location": "L198"}, {"caller_nid": "js_semester_management_updatesemesterselector", "callee": "keys", "is_member_call": true, "source_file": "C:\\Users\\maria\\Downloads\\GPAce-main\\js\\semester-management.js", "source_location": "L198"}, {"caller_nid": "js_semester_management_updatesemesterselector", "callee": "find", "is_member_call": true, "source_file": "C:\\Users\\maria\\Downloads\\GPAce-main\\js\\semester-management.js", "source_location": "L207"}, {"caller_nid": "js_semester_management_updatesemesterselector", "callee": "getElementById", "is_member_call": true, "source_file": "C:\\Users\\maria\\Downloads\\GPAce-main\\js\\semester-management.js", "source_location": "L225"}, {"caller_nid": "js_semester_management_updatesemesterselector", "callee": "getElementById", "is_member_call": true, "source_file": "C:\\Users\\maria\\Downloads\\GPAce-main\\js\\semester-management.js", "source_location": "L226"}, {"caller_nid": "js_semester_management_updatesemesterselector", "callee": "error", "is_member_call": true, "source_file": "C:\\Users\\maria\\Downloads\\GPAce-main\\js\\semester-management.js", "source_location": "L269"}, {"caller_nid": "js_semester_management_handlesemesterchange", "callee": "getElementById", "is_member_call": true, "source_file": "C:\\Users\\maria\\Downloads\\GPAce-main\\js\\semester-management.js", "source_location": "L277"}, {"caller_nid": "js_semester_management_handlesemesterchange", "callee": "info", "is_member_call": true, "source_file": "C:\\Users\\maria\\Downloads\\GPAce-main\\js\\semester-management.js", "source_location": "L298"}, {"caller_nid": "js_semester_management_handlesemesterchange", "callee": "displaySavedSubjects", "is_member_call": true, "source_file": "C:\\Users\\maria\\Downloads\\GPAce-main\\js\\semester-management.js", "source_location": "L302"}, {"caller_nid": "js_semester_management_handlesemesterchange", "callee": "warn", "is_member_call": true, "source_file": "C:\\Users\\maria\\Downloads\\GPAce-main\\js\\semester-management.js", "source_location": "L304"}, {"caller_nid": "js_semester_management_initsemestermanagement", "callee": "getStorage", "is_member_call": false, "source_file": "C:\\Users\\maria\\Downloads\\GPAce-main\\js\\semester-management.js", "source_location": "L313"}, {"caller_nid": "js_semester_management_initsemestermanagement", "callee": "log", "is_member_call": true, "source_file": "C:\\Users\\maria\\Downloads\\GPAce-main\\js\\semester-management.js", "source_location": "L316"}, {"caller_nid": "js_semester_management_initsemestermanagement", "callee": "getElementById", "is_member_call": true, "source_file": "C:\\Users\\maria\\Downloads\\GPAce-main\\js\\semester-management.js", "source_location": "L325"}, {"caller_nid": "js_semester_management_initsemestermanagement", "callee": "addEventListener", "is_member_call": true, "source_file": "C:\\Users\\maria\\Downloads\\GPAce-main\\js\\semester-management.js", "source_location": "L327"}, {"caller_nid": "js_semester_management_initsemestermanagement", "callee": "getElementById", "is_member_call": true, "source_file": "C:\\Users\\maria\\Downloads\\GPAce-main\\js\\semester-management.js", "source_location": "L331"}, {"caller_nid": "js_semester_management_initsemestermanagement", "callee": "get", "is_member_call": true, "source_file": "C:\\Users\\maria\\Downloads\\GPAce-main\\js\\semester-management.js", "source_location": "L334"}, {"caller_nid": "js_semester_management_initsemestermanagement", "callee": "addEventListener", "is_member_call": true, "source_file": "C:\\Users\\maria\\Downloads\\GPAce-main\\js\\semester-management.js", "source_location": "L337"}, {"caller_nid": "js_semester_management_initsemestermanagement", "callee": "set", "is_member_call": true, "source_file": "C:\\Users\\maria\\Downloads\\GPAce-main\\js\\semester-management.js", "source_location": "L338"}, {"caller_nid": "js_semester_management_initsemestermanagement", "callee": "log", "is_member_call": true, "source_file": "C:\\Users\\maria\\Downloads\\GPAce-main\\js\\semester-management.js", "source_location": "L353"}, {"caller_nid": "js_semester_management_initsemestermanagement", "callee": "error", "is_member_call": true, "source_file": "C:\\Users\\maria\\Downloads\\GPAce-main\\js\\semester-management.js", "source_location": "L356"}, {"caller_nid": "js_semester_management_logsemesterdebuginfo", "callee": "getStorage", "is_member_call": false, "source_file": "C:\\Users\\maria\\Downloads\\GPAce-main\\js\\semester-management.js", "source_location": "L395"}, {"caller_nid": "js_semester_management_logsemesterdebuginfo", "callee": "group", "is_member_call": true, "source_file": "C:\\Users\\maria\\Downloads\\GPAce-main\\js\\semester-management.js", "source_location": "L397"}, {"caller_nid": "js_semester_management_logsemesterdebuginfo", "callee": "log", "is_member_call": true, "source_file": "C:\\Users\\maria\\Downloads\\GPAce-main\\js\\semester-management.js", "source_location": "L398"}, {"caller_nid": "js_semester_management_logsemesterdebuginfo", "callee": "get", "is_member_call": true, "source_file": "C:\\Users\\maria\\Downloads\\GPAce-main\\js\\semester-management.js", "source_location": "L398"}, {"caller_nid": "js_semester_management_logsemesterdebuginfo", "callee": "log", "is_member_call": true, "source_file": "C:\\Users\\maria\\Downloads\\GPAce-main\\js\\semester-management.js", "source_location": "L399"}, {"caller_nid": "js_semester_management_logsemesterdebuginfo", "callee": "get", "is_member_call": true, "source_file": "C:\\Users\\maria\\Downloads\\GPAce-main\\js\\semester-management.js", "source_location": "L399"}, {"caller_nid": "js_semester_management_logsemesterdebuginfo", "callee": "get", "is_member_call": true, "source_file": "C:\\Users\\maria\\Downloads\\GPAce-main\\js\\semester-management.js", "source_location": "L401"}, {"caller_nid": "js_semester_management_logsemesterdebuginfo", "callee": "log", "is_member_call": true, "source_file": "C:\\Users\\maria\\Downloads\\GPAce-main\\js\\semester-management.js", "source_location": "L402"}, {"caller_nid": "js_semester_management_logsemesterdebuginfo", "callee": "keys", "is_member_call": true, "source_file": "C:\\Users\\maria\\Downloads\\GPAce-main\\js\\semester-management.js", "source_location": "L402"}, {"caller_nid": "js_semester_management_logsemesterdebuginfo", "callee": "keys", "is_member_call": true, "source_file": "C:\\Users\\maria\\Downloads\\GPAce-main\\js\\semester-management.js", "source_location": "L404"}, {"caller_nid": "js_semester_management_logsemesterdebuginfo", "callee": "log", "is_member_call": true, "source_file": "C:\\Users\\maria\\Downloads\\GPAce-main\\js\\semester-management.js", "source_location": "L405"}, {"caller_nid": "js_semester_management_logsemesterdebuginfo", "callee": "keys", "is_member_call": true, "source_file": "C:\\Users\\maria\\Downloads\\GPAce-main\\js\\semester-management.js", "source_location": "L405"}, {"caller_nid": "js_semester_management_logsemesterdebuginfo", "callee": "get", "is_member_call": true, "source_file": "C:\\Users\\maria\\Downloads\\GPAce-main\\js\\semester-management.js", "source_location": "L408"}, {"caller_nid": "js_semester_management_logsemesterdebuginfo", "callee": "log", "is_member_call": true, "source_file": "C:\\Users\\maria\\Downloads\\GPAce-main\\js\\semester-management.js", "source_location": "L409"}, {"caller_nid": "js_semester_management_logsemesterdebuginfo", "callee": "groupEnd", "is_member_call": true, "source_file": "C:\\Users\\maria\\Downloads\\GPAce-main\\js\\semester-management.js", "source_location": "L411"}, {"caller_nid": "js_semester_management_logsemesterdebuginfo", "callee": "error", "is_member_call": true, "source_file": "C:\\Users\\maria\\Downloads\\GPAce-main\\js\\semester-management.js", "source_location": "L413"}, {"caller_nid": "js_semester_management_migratetosemestersystem", "callee": "getStorage", "is_member_call": false, "source_file": "C:\\Users\\maria\\Downloads\\GPAce-main\\js\\semester-management.js", "source_location": "L419"}, {"caller_nid": "js_semester_management_migratetosemestersystem", "callee": "get", "is_member_call": true, "source_file": "C:\\Users\\maria\\Downloads\\GPAce-main\\js\\semester-management.js", "source_location": "L422"}, {"caller_nid": "js_semester_management_migratetosemestersystem", "callee": "get", "is_member_call": true, "source_file": "C:\\Users\\maria\\Downloads\\GPAce-main\\js\\semester-management.js", "source_location": "L427"}, {"caller_nid": "js_semester_management_migratetosemestersystem", "callee": "toISOString", "is_member_call": true, "source_file": "C:\\Users\\maria\\Downloads\\GPAce-main\\js\\semester-management.js", "source_location": "L434"}, {"caller_nid": "js_semester_management_migratetosemestersystem", "callee": "set", "is_member_call": true, "source_file": "C:\\Users\\maria\\Downloads\\GPAce-main\\js\\semester-management.js", "source_location": "L438"}, {"caller_nid": "js_semester_management_migratetosemestersystem", "callee": "set", "is_member_call": true, "source_file": "C:\\Users\\maria\\Downloads\\GPAce-main\\js\\semester-management.js", "source_location": "L439"}, {"caller_nid": "js_semester_management_migratetosemestersystem", "callee": "set", "is_member_call": true, "source_file": "C:\\Users\\maria\\Downloads\\GPAce-main\\js\\semester-management.js", "source_location": "L442"}, {"caller_nid": "js_semester_management_migratetosemestersystem", "callee": "log", "is_member_call": true, "source_file": "C:\\Users\\maria\\Downloads\\GPAce-main\\js\\semester-management.js", "source_location": "L444"}, {"caller_nid": "js_semester_management_migratetosemestersystem", "callee": "error", "is_member_call": true, "source_file": "C:\\Users\\maria\\Downloads\\GPAce-main\\js\\semester-management.js", "source_location": "L447"}, {"caller_nid": "js_semester_management_showcopysemestermodal", "callee": "getStorage", "is_member_call": false, "source_file": "C:\\Users\\maria\\Downloads\\GPAce-main\\js\\semester-management.js", "source_location": "L461"}, {"caller_nid": "js_semester_management_showcopysemestermodal", "callee": "get", "is_member_call": true, "source_file": "C:\\Users\\maria\\Downloads\\GPAce-main\\js\\semester-management.js", "source_location": "L464"}, {"caller_nid": "js_semester_management_showcopysemestermodal", "callee": "getElementById", "is_member_call": true, "source_file": "C:\\Users\\maria\\Downloads\\GPAce-main\\js\\semester-management.js", "source_location": "L465"}, {"caller_nid": "js_semester_management_showcopysemestermodal", "callee": "forEach", "is_member_call": true, "source_file": "C:\\Users\\maria\\Downloads\\GPAce-main\\js\\semester-management.js", "source_location": "L471"}, {"caller_nid": "js_semester_management_showcopysemestermodal", "callee": "keys", "is_member_call": true, "source_file": "C:\\Users\\maria\\Downloads\\GPAce-main\\js\\semester-management.js", "source_location": "L471"}, {"caller_nid": "js_semester_management_showcopysemestermodal", "callee": "getElementById", "is_member_call": true, "source_file": "C:\\Users\\maria\\Downloads\\GPAce-main\\js\\semester-management.js", "source_location": "L482"}, {"caller_nid": "js_semester_management_showcopysemestermodal", "callee": "getElementById", "is_member_call": true, "source_file": "C:\\Users\\maria\\Downloads\\GPAce-main\\js\\semester-management.js", "source_location": "L485"}, {"caller_nid": "js_semester_management_showcopysemestermodal", "callee": "show", "is_member_call": true, "source_file": "C:\\Users\\maria\\Downloads\\GPAce-main\\js\\semester-management.js", "source_location": "L486"}, {"caller_nid": "js_semester_management_showcopysemestermodal", "callee": "error", "is_member_call": true, "source_file": "C:\\Users\\maria\\Downloads\\GPAce-main\\js\\semester-management.js", "source_location": "L488"}, {"caller_nid": "js_semester_management_showcopysemestermodal", "callee": "error", "is_member_call": true, "source_file": "C:\\Users\\maria\\Downloads\\GPAce-main\\js\\semester-management.js", "source_location": "L489"}, {"caller_nid": "js_semester_management_copysubjectstonewsemester", "callee": "getStorage", "is_member_call": false, "source_file": "C:\\Users\\maria\\Downloads\\GPAce-main\\js\\semester-management.js", "source_location": "L497"}, {"caller_nid": "js_semester_management_copysubjectstonewsemester", "callee": "getElementById", "is_member_call": true, "source_file": "C:\\Users\\maria\\Downloads\\GPAce-main\\js\\semester-management.js", "source_location": "L499"}, {"caller_nid": "js_semester_management_copysubjectstonewsemester", "callee": "trim", "is_member_call": true, "source_file": "C:\\Users\\maria\\Downloads\\GPAce-main\\js\\semester-management.js", "source_location": "L500"}, {"caller_nid": "js_semester_management_copysubjectstonewsemester", "callee": "getElementById", "is_member_call": true, "source_file": "C:\\Users\\maria\\Downloads\\GPAce-main\\js\\semester-management.js", "source_location": "L500"}, {"caller_nid": "js_semester_management_copysubjectstonewsemester", "callee": "trim", "is_member_call": true, "source_file": "C:\\Users\\maria\\Downloads\\GPAce-main\\js\\semester-management.js", "source_location": "L501"}, {"caller_nid": "js_semester_management_copysubjectstonewsemester", "callee": "getElementById", "is_member_call": true, "source_file": "C:\\Users\\maria\\Downloads\\GPAce-main\\js\\semester-management.js", "source_location": "L501"}, {"caller_nid": "js_semester_management_copysubjectstonewsemester", "callee": "getElementById", "is_member_call": true, "source_file": "C:\\Users\\maria\\Downloads\\GPAce-main\\js\\semester-management.js", "source_location": "L502"}, {"caller_nid": "js_semester_management_copysubjectstonewsemester", "callee": "warning", "is_member_call": true, "source_file": "C:\\Users\\maria\\Downloads\\GPAce-main\\js\\semester-management.js", "source_location": "L505"}, {"caller_nid": "js_semester_management_copysubjectstonewsemester", "callee": "get", "is_member_call": true, "source_file": "C:\\Users\\maria\\Downloads\\GPAce-main\\js\\semester-management.js", "source_location": "L510"}, {"caller_nid": "js_semester_management_copysubjectstonewsemester", "callee": "confirm", "is_member_call": false, "source_file": "C:\\Users\\maria\\Downloads\\GPAce-main\\js\\semester-management.js", "source_location": "L514"}, {"caller_nid": "js_semester_management_copysubjectstonewsemester", "callee": "warning", "is_member_call": true, "source_file": "C:\\Users\\maria\\Downloads\\GPAce-main\\js\\semester-management.js", "source_location": "L522"}, {"caller_nid": "js_semester_management_copysubjectstonewsemester", "callee": "toISOString", "is_member_call": true, "source_file": "C:\\Users\\maria\\Downloads\\GPAce-main\\js\\semester-management.js", "source_location": "L529"}, {"caller_nid": "js_semester_management_copysubjectstonewsemester", "callee": "toISOString", "is_member_call": true, "source_file": "C:\\Users\\maria\\Downloads\\GPAce-main\\js\\semester-management.js", "source_location": "L533"}, {"caller_nid": "js_semester_management_copysubjectstonewsemester", "callee": "set", "is_member_call": true, "source_file": "C:\\Users\\maria\\Downloads\\GPAce-main\\js\\semester-management.js", "source_location": "L539"}, {"caller_nid": "js_semester_management_copysubjectstonewsemester", "callee": "saveSubjectsToFirestore", "is_member_call": true, "source_file": "C:\\Users\\maria\\Downloads\\GPAce-main\\js\\semester-management.js", "source_location": "L547"}, {"caller_nid": "js_semester_management_copysubjectstonewsemester", "callee": "toISOString", "is_member_call": true, "source_file": "C:\\Users\\maria\\Downloads\\GPAce-main\\js\\semester-management.js", "source_location": "L550"}, {"caller_nid": "js_semester_management_copysubjectstonewsemester", "callee": "set", "is_member_call": true, "source_file": "C:\\Users\\maria\\Downloads\\GPAce-main\\js\\semester-management.js", "source_location": "L551"}, {"caller_nid": "js_semester_management_copysubjectstonewsemester", "callee": "log", "is_member_call": true, "source_file": "C:\\Users\\maria\\Downloads\\GPAce-main\\js\\semester-management.js", "source_location": "L553"}, {"caller_nid": "js_semester_management_copysubjectstonewsemester", "callee": "error", "is_member_call": true, "source_file": "C:\\Users\\maria\\Downloads\\GPAce-main\\js\\semester-management.js", "source_location": "L555"}, {"caller_nid": "js_semester_management_copysubjectstonewsemester", "callee": "hide", "is_member_call": true, "source_file": "C:\\Users\\maria\\Downloads\\GPAce-main\\js\\semester-management.js", "source_location": "L561"}, {"caller_nid": "js_semester_management_copysubjectstonewsemester", "callee": "getInstance", "is_member_call": true, "source_file": "C:\\Users\\maria\\Downloads\\GPAce-main\\js\\semester-management.js", "source_location": "L561"}, {"caller_nid": "js_semester_management_copysubjectstonewsemester", "callee": "getElementById", "is_member_call": true, "source_file": "C:\\Users\\maria\\Downloads\\GPAce-main\\js\\semester-management.js", "source_location": "L561"}, {"caller_nid": "js_semester_management_copysubjectstonewsemester", "callee": "displaySavedSubjects", "is_member_call": true, "source_file": "C:\\Users\\maria\\Downloads\\GPAce-main\\js\\semester-management.js", "source_location": "L565"}, {"caller_nid": "js_semester_management_copysubjectstonewsemester", "callee": "success", "is_member_call": true, "source_file": "C:\\Users\\maria\\Downloads\\GPAce-main\\js\\semester-management.js", "source_location": "L568"}, {"caller_nid": "js_semester_management_copysubjectstonewsemester", "callee": "error", "is_member_call": true, "source_file": "C:\\Users\\maria\\Downloads\\GPAce-main\\js\\semester-management.js", "source_location": "L570"}, {"caller_nid": "js_semester_management_copysubjectstonewsemester", "callee": "error", "is_member_call": true, "source_file": "C:\\Users\\maria\\Downloads\\GPAce-main\\js\\semester-management.js", "source_location": "L571"}, {"caller_nid": "js_semester_management_shownewsemestermodal", "callee": "getElementById", "is_member_call": true, "source_file": "C:\\Users\\maria\\Downloads\\GPAce-main\\js\\semester-management.js", "source_location": "L581"}, {"caller_nid": "js_semester_management_shownewsemestermodal", "callee": "getElementById", "is_member_call": true, "source_file": "C:\\Users\\maria\\Downloads\\GPAce-main\\js\\semester-management.js", "source_location": "L582"}, {"caller_nid": "js_semester_management_shownewsemestermodal", "callee": "getElementById", "is_member_call": true, "source_file": "C:\\Users\\maria\\Downloads\\GPAce-main\\js\\semester-management.js", "source_location": "L583"}, {"caller_nid": "js_semester_management_shownewsemestermodal", "callee": "getElementById", "is_member_call": true, "source_file": "C:\\Users\\maria\\Downloads\\GPAce-main\\js\\semester-management.js", "source_location": "L586"}, {"caller_nid": "js_semester_management_shownewsemestermodal", "callee": "show", "is_member_call": true, "source_file": "C:\\Users\\maria\\Downloads\\GPAce-main\\js\\semester-management.js", "source_location": "L587"}, {"caller_nid": "js_semester_management_shownewsemestermodal", "callee": "error", "is_member_call": true, "source_file": "C:\\Users\\maria\\Downloads\\GPAce-main\\js\\semester-management.js", "source_location": "L592"}, {"caller_nid": "js_semester_management_shownewsemestermodal", "callee": "error", "is_member_call": true, "source_file": "C:\\Users\\maria\\Downloads\\GPAce-main\\js\\semester-management.js", "source_location": "L593"}, {"caller_nid": "js_semester_management_createnewsemester", "callee": "getStorage", "is_member_call": false, "source_file": "C:\\Users\\maria\\Downloads\\GPAce-main\\js\\semester-management.js", "source_location": "L601"}, {"caller_nid": "js_semester_management_createnewsemester", "callee": "getElementById", "is_member_call": true, "source_file": "C:\\Users\\maria\\Downloads\\GPAce-main\\js\\semester-management.js", "source_location": "L604"}, {"caller_nid": "js_semester_management_createnewsemester", "callee": "trim", "is_member_call": true, "source_file": "C:\\Users\\maria\\Downloads\\GPAce-main\\js\\semester-management.js", "source_location": "L605"}, {"caller_nid": "js_semester_management_createnewsemester", "callee": "trim", "is_member_call": true, "source_file": "C:\\Users\\maria\\Downloads\\GPAce-main\\js\\semester-management.js", "source_location": "L606"}, {"caller_nid": "js_semester_management_createnewsemester", "callee": "getElementById", "is_member_call": true, "source_file": "C:\\Users\\maria\\Downloads\\GPAce-main\\js\\semester-management.js", "source_location": "L606"}, {"caller_nid": "js_semester_management_createnewsemester", "callee": "getElementById", "is_member_call": true, "source_file": "C:\\Users\\maria\\Downloads\\GPAce-main\\js\\semester-management.js", "source_location": "L607"}, {"caller_nid": "js_semester_management_createnewsemester", "callee": "add", "is_member_call": true, "source_file": "C:\\Users\\maria\\Downloads\\GPAce-main\\js\\semester-management.js", "source_location": "L611"}, {"caller_nid": "js_semester_management_createnewsemester", "callee": "getElementById", "is_member_call": true, "source_file": "C:\\Users\\maria\\Downloads\\GPAce-main\\js\\semester-management.js", "source_location": "L613"}, {"caller_nid": "js_semester_management_createnewsemester", "callee": "createElement", "is_member_call": true, "source_file": "C:\\Users\\maria\\Downloads\\GPAce-main\\js\\semester-management.js", "source_location": "L614"}, {"caller_nid": "js_semester_management_createnewsemester", "callee": "appendChild", "is_member_call": true, "source_file": "C:\\Users\\maria\\Downloads\\GPAce-main\\js\\semester-management.js", "source_location": "L618"}, {"caller_nid": "js_semester_management_createnewsemester", "callee": "remove", "is_member_call": true, "source_file": "C:\\Users\\maria\\Downloads\\GPAce-main\\js\\semester-management.js", "source_location": "L622"}, {"caller_nid": "js_semester_management_createnewsemester", "callee": "get", "is_member_call": true, "source_file": "C:\\Users\\maria\\Downloads\\GPAce-main\\js\\semester-management.js", "source_location": "L626"}, {"caller_nid": "js_semester_management_createnewsemester", "callee": "confirm", "is_member_call": true, "source_file": "C:\\Users\\maria\\Downloads\\GPAce-main\\js\\semester-management.js", "source_location": "L631"}, {"caller_nid": "js_semester_management_createnewsemester", "callee": "querySelector", "is_member_call": true, "source_file": "C:\\Users\\maria\\Downloads\\GPAce-main\\js\\semester-management.js", "source_location": "L637"}, {"caller_nid": "js_semester_management_createnewsemester", "callee": "toISOString", "is_member_call": true, "source_file": "C:\\Users\\maria\\Downloads\\GPAce-main\\js\\semester-management.js", "source_location": "L648"}, {"caller_nid": "js_semester_management_createnewsemester", "callee": "toISOString", "is_member_call": true, "source_file": "C:\\Users\\maria\\Downloads\\GPAce-main\\js\\semester-management.js", "source_location": "L651"}, {"caller_nid": "js_semester_management_createnewsemester", "callee": "set", "is_member_call": true, "source_file": "C:\\Users\\maria\\Downloads\\GPAce-main\\js\\semester-management.js", "source_location": "L657"}, {"caller_nid": "js_semester_management_createnewsemester", "callee": "saveSubjectsToFirestore", "is_member_call": true, "source_file": "C:\\Users\\maria\\Downloads\\GPAce-main\\js\\semester-management.js", "source_location": "L665"}, {"caller_nid": "js_semester_management_createnewsemester", "callee": "set", "is_member_call": true, "source_file": "C:\\Users\\maria\\Downloads\\GPAce-main\\js\\semester-management.js", "source_location": "L667"}, {"caller_nid": "js_semester_management_createnewsemester", "callee": "log", "is_member_call": true, "source_file": "C:\\Users\\maria\\Downloads\\GPAce-main\\js\\semester-management.js", "source_location": "L668"}, {"caller_nid": "js_semester_management_createnewsemester", "callee": "error", "is_member_call": true, "source_file": "C:\\Users\\maria\\Downloads\\GPAce-main\\js\\semester-management.js", "source_location": "L670"}, {"caller_nid": "js_semester_management_createnewsemester", "callee": "hide", "is_member_call": true, "source_file": "C:\\Users\\maria\\Downloads\\GPAce-main\\js\\semester-management.js", "source_location": "L676"}, {"caller_nid": "js_semester_management_createnewsemester", "callee": "getInstance", "is_member_call": true, "source_file": "C:\\Users\\maria\\Downloads\\GPAce-main\\js\\semester-management.js", "source_location": "L676"}, {"caller_nid": "js_semester_management_createnewsemester", "callee": "getElementById", "is_member_call": true, "source_file": "C:\\Users\\maria\\Downloads\\GPAce-main\\js\\semester-management.js", "source_location": "L676"}, {"caller_nid": "js_semester_management_createnewsemester", "callee": "getElementById", "is_member_call": true, "source_file": "C:\\Users\\maria\\Downloads\\GPAce-main\\js\\semester-management.js", "source_location": "L679"}, {"caller_nid": "js_semester_management_createnewsemester", "callee": "getElementById", "is_member_call": true, "source_file": "C:\\Users\\maria\\Downloads\\GPAce-main\\js\\semester-management.js", "source_location": "L680"}, {"caller_nid": "js_semester_management_createnewsemester", "callee": "setTimeout", "is_member_call": false, "source_file": "C:\\Users\\maria\\Downloads\\GPAce-main\\js\\semester-management.js", "source_location": "L683"}, {"caller_nid": "js_semester_management_createnewsemester", "callee": "error", "is_member_call": true, "source_file": "C:\\Users\\maria\\Downloads\\GPAce-main\\js\\semester-management.js", "source_location": "L697"}, {"caller_nid": "js_semester_management_createnewsemester", "callee": "error", "is_member_call": true, "source_file": "C:\\Users\\maria\\Downloads\\GPAce-main\\js\\semester-management.js", "source_location": "L698"}, {"caller_nid": "js_semester_management_createnewsemester", "callee": "querySelector", "is_member_call": true, "source_file": "C:\\Users\\maria\\Downloads\\GPAce-main\\js\\semester-management.js", "source_location": "L701"}, {"caller_nid": "js_semester_management_setupsemestertemplatebuttons", "callee": "querySelectorAll", "is_member_call": true, "source_file": "C:\\Users\\maria\\Downloads\\GPAce-main\\js\\semester-management.js", "source_location": "L712"}, {"caller_nid": "js_semester_management_setupsemestertemplatebuttons", "callee": "getElementById", "is_member_call": true, "source_file": "C:\\Users\\maria\\Downloads\\GPAce-main\\js\\semester-management.js", "source_location": "L713"}, {"caller_nid": "js_semester_management_setupsemestertemplatebuttons", "callee": "forEach", "is_member_call": true, "source_file": "C:\\Users\\maria\\Downloads\\GPAce-main\\js\\semester-management.js", "source_location": "L717"}, {"caller_nid": "js_semester_management_updatesemesterpreview", "callee": "getElementById", "is_member_call": true, "source_file": "C:\\Users\\maria\\Downloads\\GPAce-main\\js\\semester-management.js", "source_location": "L738"}, {"caller_nid": "js_semester_management_updatesemesterpreview", "callee": "getElementById", "is_member_call": true, "source_file": "C:\\Users\\maria\\Downloads\\GPAce-main\\js\\semester-management.js", "source_location": "L739"}, {"caller_nid": "js_semester_management_updatesemesterpreview", "callee": "getElementById", "is_member_call": true, "source_file": "C:\\Users\\maria\\Downloads\\GPAce-main\\js\\semester-management.js", "source_location": "L740"}, {"caller_nid": "js_semester_management_updatesemesterpreview", "callee": "getElementById", "is_member_call": true, "source_file": "C:\\Users\\maria\\Downloads\\GPAce-main\\js\\semester-management.js", "source_location": "L741"}, {"caller_nid": "js_semester_management_updatesemesterpreview", "callee": "getElementById", "is_member_call": true, "source_file": "C:\\Users\\maria\\Downloads\\GPAce-main\\js\\semester-management.js", "source_location": "L744"}, {"caller_nid": "js_semester_management_updatesemesterpreview", "callee": "getElementById", "is_member_call": true, "source_file": "C:\\Users\\maria\\Downloads\\GPAce-main\\js\\semester-management.js", "source_location": "L745"}, {"caller_nid": "js_semester_management_updatesemesterpreview", "callee": "getElementById", "is_member_call": true, "source_file": "C:\\Users\\maria\\Downloads\\GPAce-main\\js\\semester-management.js", "source_location": "L746"}, {"caller_nid": "js_semester_management_selectcolortag", "callee": "forEach", "is_member_call": true, "source_file": "C:\\Users\\maria\\Downloads\\GPAce-main\\js\\semester-management.js", "source_location": "L775"}, {"caller_nid": "js_semester_management_selectcolortag", "callee": "querySelectorAll", "is_member_call": true, "source_file": "C:\\Users\\maria\\Downloads\\GPAce-main\\js\\semester-management.js", "source_location": "L775"}, {"caller_nid": "js_semester_management_selectcolortag", "callee": "add", "is_member_call": true, "source_file": "C:\\Users\\maria\\Downloads\\GPAce-main\\js\\semester-management.js", "source_location": "L780"}, {"caller_nid": "js_semester_management_selectcolortag", "callee": "getElementById", "is_member_call": true, "source_file": "C:\\Users\\maria\\Downloads\\GPAce-main\\js\\semester-management.js", "source_location": "L783"}, {"caller_nid": "js_semester_management_editsemesterdetails", "callee": "getStorage", "is_member_call": false, "source_file": "C:\\Users\\maria\\Downloads\\GPAce-main\\js\\semester-management.js", "source_location": "L793"}, {"caller_nid": "js_semester_management_editsemesterdetails", "callee": "alert", "is_member_call": false, "source_file": "C:\\Users\\maria\\Downloads\\GPAce-main\\js\\semester-management.js", "source_location": "L795"}, {"caller_nid": "js_semester_management_editsemesterdetails", "callee": "get", "is_member_call": true, "source_file": "C:\\Users\\maria\\Downloads\\GPAce-main\\js\\semester-management.js", "source_location": "L801"}, {"caller_nid": "js_semester_management_editsemesterdetails", "callee": "alert", "is_member_call": false, "source_file": "C:\\Users\\maria\\Downloads\\GPAce-main\\js\\semester-management.js", "source_location": "L805"}, {"caller_nid": "js_semester_management_editsemesterdetails", "callee": "getElementById", "is_member_call": true, "source_file": "C:\\Users\\maria\\Downloads\\GPAce-main\\js\\semester-management.js", "source_location": "L810"}, {"caller_nid": "js_semester_management_editsemesterdetails", "callee": "getElementById", "is_member_call": true, "source_file": "C:\\Users\\maria\\Downloads\\GPAce-main\\js\\semester-management.js", "source_location": "L811"}, {"caller_nid": "js_semester_management_editsemesterdetails", "callee": "getElementById", "is_member_call": true, "source_file": "C:\\Users\\maria\\Downloads\\GPAce-main\\js\\semester-management.js", "source_location": "L812"}, {"caller_nid": "js_semester_management_editsemesterdetails", "callee": "remove", "is_member_call": true, "source_file": "C:\\Users\\maria\\Downloads\\GPAce-main\\js\\semester-management.js", "source_location": "L815"}, {"caller_nid": "js_semester_management_editsemesterdetails", "callee": "getElementById", "is_member_call": true, "source_file": "C:\\Users\\maria\\Downloads\\GPAce-main\\js\\semester-management.js", "source_location": "L815"}, {"caller_nid": "js_semester_management_editsemesterdetails", "callee": "getElementById", "is_member_call": true, "source_file": "C:\\Users\\maria\\Downloads\\GPAce-main\\js\\semester-management.js", "source_location": "L819"}, {"caller_nid": "js_semester_management_editsemesterdetails", "callee": "forEach", "is_member_call": true, "source_file": "C:\\Users\\maria\\Downloads\\GPAce-main\\js\\semester-management.js", "source_location": "L822"}, {"caller_nid": "js_semester_management_editsemesterdetails", "callee": "querySelectorAll", "is_member_call": true, "source_file": "C:\\Users\\maria\\Downloads\\GPAce-main\\js\\semester-management.js", "source_location": "L822"}, {"caller_nid": "js_semester_management_editsemesterdetails", "callee": "getElementById", "is_member_call": true, "source_file": "C:\\Users\\maria\\Downloads\\GPAce-main\\js\\semester-management.js", "source_location": "L836"}, {"caller_nid": "js_semester_management_editsemesterdetails", "callee": "show", "is_member_call": true, "source_file": "C:\\Users\\maria\\Downloads\\GPAce-main\\js\\semester-management.js", "source_location": "L837"}, {"caller_nid": "js_semester_management_editsemesterdetails", "callee": "error", "is_member_call": true, "source_file": "C:\\Users\\maria\\Downloads\\GPAce-main\\js\\semester-management.js", "source_location": "L840"}, {"caller_nid": "js_semester_management_editsemesterdetails", "callee": "alert", "is_member_call": false, "source_file": "C:\\Users\\maria\\Downloads\\GPAce-main\\js\\semester-management.js", "source_location": "L841"}, {"caller_nid": "js_semester_management_savesemesterdetails", "callee": "getStorage", "is_member_call": false, "source_file": "C:\\Users\\maria\\Downloads\\GPAce-main\\js\\semester-management.js", "source_location": "L849"}, {"caller_nid": "js_semester_management_savesemesterdetails", "callee": "trim", "is_member_call": true, "source_file": "C:\\Users\\maria\\Downloads\\GPAce-main\\js\\semester-management.js", "source_location": "L851"}, {"caller_nid": "js_semester_management_savesemesterdetails", "callee": "getElementById", "is_member_call": true, "source_file": "C:\\Users\\maria\\Downloads\\GPAce-main\\js\\semester-management.js", "source_location": "L851"}, {"caller_nid": "js_semester_management_savesemesterdetails", "callee": "trim", "is_member_call": true, "source_file": "C:\\Users\\maria\\Downloads\\GPAce-main\\js\\semester-management.js", "source_location": "L852"}, {"caller_nid": "js_semester_management_savesemesterdetails", "callee": "getElementById", "is_member_call": true, "source_file": "C:\\Users\\maria\\Downloads\\GPAce-main\\js\\semester-management.js", "source_location": "L852"}, {"caller_nid": "js_semester_management_savesemesterdetails", "callee": "getElementById", "is_member_call": true, "source_file": "C:\\Users\\maria\\Downloads\\GPAce-main\\js\\semester-management.js", "source_location": "L853"}, {"caller_nid": "js_semester_management_savesemesterdetails", "callee": "getElementById", "is_member_call": true, "source_file": "C:\\Users\\maria\\Downloads\\GPAce-main\\js\\semester-management.js", "source_location": "L854"}, {"caller_nid": "js_semester_management_savesemesterdetails", "callee": "alert", "is_member_call": false, "source_file": "C:\\Users\\maria\\Downloads\\GPAce-main\\js\\semester-management.js", "source_location": "L857"}, {"caller_nid": "js_semester_management_savesemesterdetails", "callee": "get", "is_member_call": true, "source_file": "C:\\Users\\maria\\Downloads\\GPAce-main\\js\\semester-management.js", "source_location": "L862"}, {"caller_nid": "js_semester_management_savesemesterdetails", "callee": "alert", "is_member_call": false, "source_file": "C:\\Users\\maria\\Downloads\\GPAce-main\\js\\semester-management.js", "source_location": "L866"}, {"caller_nid": "js_semester_management_savesemesterdetails", "callee": "confirm", "is_member_call": false, "source_file": "C:\\Users\\maria\\Downloads\\GPAce-main\\js\\semester-management.js", "source_location": "L872"}, {"caller_nid": "js_semester_management_savesemesterdetails", "callee": "toISOString", "is_member_call": true, "source_file": "C:\\Users\\maria\\Downloads\\GPAce-main\\js\\semester-management.js", "source_location": "L883"}, {"caller_nid": "js_semester_management_savesemesterdetails", "callee": "set", "is_member_call": true, "source_file": "C:\\Users\\maria\\Downloads\\GPAce-main\\js\\semester-management.js", "source_location": "L894"}, {"caller_nid": "js_semester_management_savesemesterdetails", "callee": "set", "is_member_call": true, "source_file": "C:\\Users\\maria\\Downloads\\GPAce-main\\js\\semester-management.js", "source_location": "L901"}, {"caller_nid": "js_semester_management_savesemesterdetails", "callee": "catch", "is_member_call": true, "source_file": "C:\\Users\\maria\\Downloads\\GPAce-main\\js\\semester-management.js", "source_location": "L906"}, {"caller_nid": "js_semester_management_savesemesterdetails", "callee": "then", "is_member_call": true, "source_file": "C:\\Users\\maria\\Downloads\\GPAce-main\\js\\semester-management.js", "source_location": "L906"}, {"caller_nid": "js_semester_management_savesemesterdetails", "callee": "then", "is_member_call": true, "source_file": "C:\\Users\\maria\\Downloads\\GPAce-main\\js\\semester-management.js", "source_location": "L906"}, {"caller_nid": "js_semester_management_savesemesterdetails", "callee": "saveSubjectsToFirestore", "is_member_call": true, "source_file": "C:\\Users\\maria\\Downloads\\GPAce-main\\js\\semester-management.js", "source_location": "L906"}, {"caller_nid": "js_semester_management_savesemesterdetails", "callee": "displaySavedSubjects", "is_member_call": false, "source_file": "C:\\Users\\maria\\Downloads\\GPAce-main\\js\\semester-management.js", "source_location": "L925"}, {"caller_nid": "js_semester_management_savesemesterdetails", "callee": "hide", "is_member_call": true, "source_file": "C:\\Users\\maria\\Downloads\\GPAce-main\\js\\semester-management.js", "source_location": "L929"}, {"caller_nid": "js_semester_management_savesemesterdetails", "callee": "getInstance", "is_member_call": true, "source_file": "C:\\Users\\maria\\Downloads\\GPAce-main\\js\\semester-management.js", "source_location": "L929"}, {"caller_nid": "js_semester_management_savesemesterdetails", "callee": "getElementById", "is_member_call": true, "source_file": "C:\\Users\\maria\\Downloads\\GPAce-main\\js\\semester-management.js", "source_location": "L929"}, {"caller_nid": "js_semester_management_savesemesterdetails", "callee": "createElement", "is_member_call": true, "source_file": "C:\\Users\\maria\\Downloads\\GPAce-main\\js\\semester-management.js", "source_location": "L948"}, {"caller_nid": "js_semester_management_savesemesterdetails", "callee": "appendChild", "is_member_call": true, "source_file": "C:\\Users\\maria\\Downloads\\GPAce-main\\js\\semester-management.js", "source_location": "L950"}, {"caller_nid": "js_semester_management_savesemesterdetails", "callee": "setTimeout", "is_member_call": false, "source_file": "C:\\Users\\maria\\Downloads\\GPAce-main\\js\\semester-management.js", "source_location": "L953"}, {"caller_nid": "js_semester_management_savesemesterdetails", "callee": "error", "is_member_call": true, "source_file": "C:\\Users\\maria\\Downloads\\GPAce-main\\js\\semester-management.js", "source_location": "L958"}, {"caller_nid": "js_semester_management_savesemesterdetails", "callee": "alert", "is_member_call": false, "source_file": "C:\\Users\\maria\\Downloads\\GPAce-main\\js\\semester-management.js", "source_location": "L959"}, {"caller_nid": "js_semester_management_archivesemester", "callee": "alert", "is_member_call": false, "source_file": "C:\\Users\\maria\\Downloads\\GPAce-main\\js\\semester-management.js", "source_location": "L969"}, {"caller_nid": "js_semester_management_archivesemester", "callee": "getElementById", "is_member_call": true, "source_file": "C:\\Users\\maria\\Downloads\\GPAce-main\\js\\semester-management.js", "source_location": "L974"}, {"caller_nid": "js_semester_management_archivesemester", "callee": "getElementById", "is_member_call": true, "source_file": "C:\\Users\\maria\\Downloads\\GPAce-main\\js\\semester-management.js", "source_location": "L977"}, {"caller_nid": "js_semester_management_archivesemester", "callee": "getElementById", "is_member_call": true, "source_file": "C:\\Users\\maria\\Downloads\\GPAce-main\\js\\semester-management.js", "source_location": "L982"}, {"caller_nid": "js_semester_management_archivesemester", "callee": "show", "is_member_call": true, "source_file": "C:\\Users\\maria\\Downloads\\GPAce-main\\js\\semester-management.js", "source_location": "L983"}, {"caller_nid": "js_semester_management_confirmarchivesemester", "callee": "getStorage", "is_member_call": false, "source_file": "C:\\Users\\maria\\Downloads\\GPAce-main\\js\\semester-management.js", "source_location": "L990"}, {"caller_nid": "js_semester_management_confirmarchivesemester", "callee": "getElementById", "is_member_call": true, "source_file": "C:\\Users\\maria\\Downloads\\GPAce-main\\js\\semester-management.js", "source_location": "L993"}, {"caller_nid": "js_semester_management_confirmarchivesemester", "callee": "get", "is_member_call": true, "source_file": "C:\\Users\\maria\\Downloads\\GPAce-main\\js\\semester-management.js", "source_location": "L999"}, {"caller_nid": "js_semester_management_confirmarchivesemester", "callee": "alert", "is_member_call": false, "source_file": "C:\\Users\\maria\\Downloads\\GPAce-main\\js\\semester-management.js", "source_location": "L1004"}, {"caller_nid": "js_semester_management_confirmarchivesemester", "callee": "toISOString", "is_member_call": true, "source_file": "C:\\Users\\maria\\Downloads\\GPAce-main\\js\\semester-management.js", "source_location": "L1012"}, {"caller_nid": "js_semester_management_confirmarchivesemester", "callee": "set", "is_member_call": true, "source_file": "C:\\Users\\maria\\Downloads\\GPAce-main\\js\\semester-management.js", "source_location": "L1016"}, {"caller_nid": "js_semester_management_confirmarchivesemester", "callee": "catch", "is_member_call": true, "source_file": "C:\\Users\\maria\\Downloads\\GPAce-main\\js\\semester-management.js", "source_location": "L1020"}, {"caller_nid": "js_semester_management_confirmarchivesemester", "callee": "then", "is_member_call": true, "source_file": "C:\\Users\\maria\\Downloads\\GPAce-main\\js\\semester-management.js", "source_location": "L1020"}, {"caller_nid": "js_semester_management_confirmarchivesemester", "callee": "saveSubjectsToFirestore", "is_member_call": true, "source_file": "C:\\Users\\maria\\Downloads\\GPAce-main\\js\\semester-management.js", "source_location": "L1020"}, {"caller_nid": "js_semester_management_confirmarchivesemester", "callee": "hide", "is_member_call": true, "source_file": "C:\\Users\\maria\\Downloads\\GPAce-main\\js\\semester-management.js", "source_location": "L1033"}, {"caller_nid": "js_semester_management_confirmarchivesemester", "callee": "getInstance", "is_member_call": true, "source_file": "C:\\Users\\maria\\Downloads\\GPAce-main\\js\\semester-management.js", "source_location": "L1033"}, {"caller_nid": "js_semester_management_confirmarchivesemester", "callee": "getElementById", "is_member_call": true, "source_file": "C:\\Users\\maria\\Downloads\\GPAce-main\\js\\semester-management.js", "source_location": "L1033"}, {"caller_nid": "js_semester_management_confirmarchivesemester", "callee": "displaySavedSubjects", "is_member_call": true, "source_file": "C:\\Users\\maria\\Downloads\\GPAce-main\\js\\semester-management.js", "source_location": "L1037"}, {"caller_nid": "js_semester_management_confirmarchivesemester", "callee": "createElement", "is_member_call": true, "source_file": "C:\\Users\\maria\\Downloads\\GPAce-main\\js\\semester-management.js", "source_location": "L1056"}, {"caller_nid": "js_semester_management_confirmarchivesemester", "callee": "appendChild", "is_member_call": true, "source_file": "C:\\Users\\maria\\Downloads\\GPAce-main\\js\\semester-management.js", "source_location": "L1058"}, {"caller_nid": "js_semester_management_confirmarchivesemester", "callee": "setTimeout", "is_member_call": false, "source_file": "C:\\Users\\maria\\Downloads\\GPAce-main\\js\\semester-management.js", "source_location": "L1061"}, {"caller_nid": "js_semester_management_confirmarchivesemester", "callee": "error", "is_member_call": true, "source_file": "C:\\Users\\maria\\Downloads\\GPAce-main\\js\\semester-management.js", "source_location": "L1066"}, {"caller_nid": "js_semester_management_confirmarchivesemester", "callee": "alert", "is_member_call": false, "source_file": "C:\\Users\\maria\\Downloads\\GPAce-main\\js\\semester-management.js", "source_location": "L1067"}, {"caller_nid": "js_semester_management_confirmarchivesemester", "callee": "getElementById", "is_member_call": true, "source_file": "C:\\Users\\maria\\Downloads\\GPAce-main\\js\\semester-management.js", "source_location": "L1070"}, {"caller_nid": "js_semester_management_deletesemester", "callee": "alert", "is_member_call": false, "source_file": "C:\\Users\\maria\\Downloads\\GPAce-main\\js\\semester-management.js", "source_location": "L1082"}, {"caller_nid": "js_semester_management_deletesemester", "callee": "getElementById", "is_member_call": true, "source_file": "C:\\Users\\maria\\Downloads\\GPAce-main\\js\\semester-management.js", "source_location": "L1087"}, {"caller_nid": "js_semester_management_deletesemester", "callee": "getElementById", "is_member_call": true, "source_file": "C:\\Users\\maria\\Downloads\\GPAce-main\\js\\semester-management.js", "source_location": "L1091"}, {"caller_nid": "js_semester_management_deletesemester", "callee": "getElementById", "is_member_call": true, "source_file": "C:\\Users\\maria\\Downloads\\GPAce-main\\js\\semester-management.js", "source_location": "L1094"}, {"caller_nid": "js_semester_management_deletesemester", "callee": "remove", "is_member_call": true, "source_file": "C:\\Users\\maria\\Downloads\\GPAce-main\\js\\semester-management.js", "source_location": "L1096"}, {"caller_nid": "js_semester_management_deletesemester", "callee": "getElementById", "is_member_call": true, "source_file": "C:\\Users\\maria\\Downloads\\GPAce-main\\js\\semester-management.js", "source_location": "L1099"}, {"caller_nid": "js_semester_management_deletesemester", "callee": "addEventListener", "is_member_call": true, "source_file": "C:\\Users\\maria\\Downloads\\GPAce-main\\js\\semester-management.js", "source_location": "L1102"}, {"caller_nid": "js_semester_management_deletesemester", "callee": "getElementById", "is_member_call": true, "source_file": "C:\\Users\\maria\\Downloads\\GPAce-main\\js\\semester-management.js", "source_location": "L1104"}, {"caller_nid": "js_semester_management_deletesemester", "callee": "add", "is_member_call": true, "source_file": "C:\\Users\\maria\\Downloads\\GPAce-main\\js\\semester-management.js", "source_location": "L1107"}, {"caller_nid": "js_semester_management_deletesemester", "callee": "remove", "is_member_call": true, "source_file": "C:\\Users\\maria\\Downloads\\GPAce-main\\js\\semester-management.js", "source_location": "L1109"}, {"caller_nid": "js_semester_management_deletesemester", "callee": "getElementById", "is_member_call": true, "source_file": "C:\\Users\\maria\\Downloads\\GPAce-main\\js\\semester-management.js", "source_location": "L1114"}, {"caller_nid": "js_semester_management_deletesemester", "callee": "getElementById", "is_member_call": true, "source_file": "C:\\Users\\maria\\Downloads\\GPAce-main\\js\\semester-management.js", "source_location": "L1121"}, {"caller_nid": "js_semester_management_deletesemester", "callee": "show", "is_member_call": true, "source_file": "C:\\Users\\maria\\Downloads\\GPAce-main\\js\\semester-management.js", "source_location": "L1122"}, {"caller_nid": "js_semester_management_confirmdeletesemester", "callee": "getStorage", "is_member_call": false, "source_file": "C:\\Users\\maria\\Downloads\\GPAce-main\\js\\semester-management.js", "source_location": "L1129"}, {"caller_nid": "js_semester_management_confirmdeletesemester", "callee": "getElementById", "is_member_call": true, "source_file": "C:\\Users\\maria\\Downloads\\GPAce-main\\js\\semester-management.js", "source_location": "L1132"}, {"caller_nid": "js_semester_management_confirmdeletesemester", "callee": "get", "is_member_call": true, "source_file": "C:\\Users\\maria\\Downloads\\GPAce-main\\js\\semester-management.js", "source_location": "L1141"}, {"caller_nid": "js_semester_management_confirmdeletesemester", "callee": "set", "is_member_call": true, "source_file": "C:\\Users\\maria\\Downloads\\GPAce-main\\js\\semester-management.js", "source_location": "L1147"}, {"caller_nid": "js_semester_management_confirmdeletesemester", "callee": "hide", "is_member_call": true, "source_file": "C:\\Users\\maria\\Downloads\\GPAce-main\\js\\semester-management.js", "source_location": "L1153"}, {"caller_nid": "js_semester_management_confirmdeletesemester", "callee": "getInstance", "is_member_call": true, "source_file": "C:\\Users\\maria\\Downloads\\GPAce-main\\js\\semester-management.js", "source_location": "L1153"}, {"caller_nid": "js_semester_management_confirmdeletesemester", "callee": "getElementById", "is_member_call": true, "source_file": "C:\\Users\\maria\\Downloads\\GPAce-main\\js\\semester-management.js", "source_location": "L1153"}, {"caller_nid": "js_semester_management_confirmdeletesemester", "callee": "catch", "is_member_call": true, "source_file": "C:\\Users\\maria\\Downloads\\GPAce-main\\js\\semester-management.js", "source_location": "L1157"}, {"caller_nid": "js_semester_management_confirmdeletesemester", "callee": "then", "is_member_call": true, "source_file": "C:\\Users\\maria\\Downloads\\GPAce-main\\js\\semester-management.js", "source_location": "L1157"}, {"caller_nid": "js_semester_management_confirmdeletesemester", "callee": "import", "is_member_call": false, "source_file": "C:\\Users\\maria\\Downloads\\GPAce-main\\js\\semester-management.js", "source_location": "L1157"}, {"caller_nid": "js_semester_management_confirmdeletesemester", "callee": "displaySavedSubjects", "is_member_call": true, "source_file": "C:\\Users\\maria\\Downloads\\GPAce-main\\js\\semester-management.js", "source_location": "L1170"}, {"caller_nid": "js_semester_management_confirmdeletesemester", "callee": "createElement", "is_member_call": true, "source_file": "C:\\Users\\maria\\Downloads\\GPAce-main\\js\\semester-management.js", "source_location": "L1189"}, {"caller_nid": "js_semester_management_confirmdeletesemester", "callee": "appendChild", "is_member_call": true, "source_file": "C:\\Users\\maria\\Downloads\\GPAce-main\\js\\semester-management.js", "source_location": "L1191"}, {"caller_nid": "js_semester_management_confirmdeletesemester", "callee": "setTimeout", "is_member_call": false, "source_file": "C:\\Users\\maria\\Downloads\\GPAce-main\\js\\semester-management.js", "source_location": "L1194"}, {"caller_nid": "js_semester_management_confirmdeletesemester", "callee": "error", "is_member_call": true, "source_file": "C:\\Users\\maria\\Downloads\\GPAce-main\\js\\semester-management.js", "source_location": "L1199"}, {"caller_nid": "js_semester_management_confirmdeletesemester", "callee": "alert", "is_member_call": false, "source_file": "C:\\Users\\maria\\Downloads\\GPAce-main\\js\\semester-management.js", "source_location": "L1200"}, {"caller_nid": "js_semester_management_confirmdeletesemester", "callee": "getElementById", "is_member_call": true, "source_file": "C:\\Users\\maria\\Downloads\\GPAce-main\\js\\semester-management.js", "source_location": "L1203"}, {"caller_nid": "js_semester_management_forcesyncsemester", "callee": "getStorage", "is_member_call": false, "source_file": "C:\\Users\\maria\\Downloads\\GPAce-main\\js\\semester-management.js", "source_location": "L1213"}, {"caller_nid": "js_semester_management_forcesyncsemester", "callee": "alert", "is_member_call": false, "source_file": "C:\\Users\\maria\\Downloads\\GPAce-main\\js\\semester-management.js", "source_location": "L1215"}, {"caller_nid": "js_semester_management_forcesyncsemester", "callee": "alert", "is_member_call": false, "source_file": "C:\\Users\\maria\\Downloads\\GPAce-main\\js\\semester-management.js", "source_location": "L1220"}, {"caller_nid": "js_semester_management_forcesyncsemester", "callee": "get", "is_member_call": true, "source_file": "C:\\Users\\maria\\Downloads\\GPAce-main\\js\\semester-management.js", "source_location": "L1225"}, {"caller_nid": "js_semester_management_forcesyncsemester", "callee": "alert", "is_member_call": false, "source_file": "C:\\Users\\maria\\Downloads\\GPAce-main\\js\\semester-management.js", "source_location": "L1229"}, {"caller_nid": "js_semester_management_forcesyncsemester", "callee": "getElementById", "is_member_call": true, "source_file": "C:\\Users\\maria\\Downloads\\GPAce-main\\js\\semester-management.js", "source_location": "L1234"}, {"caller_nid": "js_semester_management_forcesyncsemester", "callee": "catch", "is_member_call": true, "source_file": "C:\\Users\\maria\\Downloads\\GPAce-main\\js\\semester-management.js", "source_location": "L1240"}, {"caller_nid": "js_semester_management_forcesyncsemester", "callee": "then", "is_member_call": true, "source_file": "C:\\Users\\maria\\Downloads\\GPAce-main\\js\\semester-management.js", "source_location": "L1240"}, {"caller_nid": "js_semester_management_forcesyncsemester", "callee": "saveSubjectsToFirestore", "is_member_call": true, "source_file": "C:\\Users\\maria\\Downloads\\GPAce-main\\js\\semester-management.js", "source_location": "L1240"}, {"caller_nid": "js_semester_management_forcesyncsemester", "callee": "error", "is_member_call": true, "source_file": "C:\\Users\\maria\\Downloads\\GPAce-main\\js\\semester-management.js", "source_location": "L1259"}, {"caller_nid": "js_semester_management_forcesyncsemester", "callee": "alert", "is_member_call": false, "source_file": "C:\\Users\\maria\\Downloads\\GPAce-main\\js\\semester-management.js", "source_location": "L1260"}, {"caller_nid": "js_semester_management_updatesyncstatus", "callee": "getStorage", "is_member_call": false, "source_file": "C:\\Users\\maria\\Downloads\\GPAce-main\\js\\semester-management.js", "source_location": "L1268"}, {"caller_nid": "js_semester_management_updatesyncstatus", "callee": "getElementById", "is_member_call": true, "source_file": "C:\\Users\\maria\\Downloads\\GPAce-main\\js\\semester-management.js", "source_location": "L1270"}, {"caller_nid": "js_semester_management_updatesyncstatus", "callee": "getElementById", "is_member_call": true, "source_file": "C:\\Users\\maria\\Downloads\\GPAce-main\\js\\semester-management.js", "source_location": "L1271"}, {"caller_nid": "js_semester_management_updatesyncstatus", "callee": "getElementById", "is_member_call": true, "source_file": "C:\\Users\\maria\\Downloads\\GPAce-main\\js\\semester-management.js", "source_location": "L1272"}, {"caller_nid": "js_semester_management_updatesyncstatus", "callee": "add", "is_member_call": true, "source_file": "C:\\Users\\maria\\Downloads\\GPAce-main\\js\\semester-management.js", "source_location": "L1277"}, {"caller_nid": "js_semester_management_updatesyncstatus", "callee": "add", "is_member_call": true, "source_file": "C:\\Users\\maria\\Downloads\\GPAce-main\\js\\semester-management.js", "source_location": "L1278"}, {"caller_nid": "js_semester_management_updatesyncstatus", "callee": "get", "is_member_call": true, "source_file": "C:\\Users\\maria\\Downloads\\GPAce-main\\js\\semester-management.js", "source_location": "L1285"}, {"caller_nid": "js_semester_management_updatesyncstatus", "callee": "remove", "is_member_call": true, "source_file": "C:\\Users\\maria\\Downloads\\GPAce-main\\js\\semester-management.js", "source_location": "L1292"}, {"caller_nid": "js_semester_management_updatesyncstatus", "callee": "round", "is_member_call": true, "source_file": "C:\\Users\\maria\\Downloads\\GPAce-main\\js\\semester-management.js", "source_location": "L1298"}, {"caller_nid": "js_semester_management_updatesyncstatus", "callee": "round", "is_member_call": true, "source_file": "C:\\Users\\maria\\Downloads\\GPAce-main\\js\\semester-management.js", "source_location": "L1305"}, {"caller_nid": "js_semester_management_updatesyncstatus", "callee": "remove", "is_member_call": true, "source_file": "C:\\Users\\maria\\Downloads\\GPAce-main\\js\\semester-management.js", "source_location": "L1311"}, {"caller_nid": "js_semester_management_updatesyncstatus", "callee": "error", "is_member_call": true, "source_file": "C:\\Users\\maria\\Downloads\\GPAce-main\\js\\semester-management.js", "source_location": "L1321"}, {"caller_nid": "js_semester_management_updatestorageusage", "callee": "getElementById", "is_member_call": true, "source_file": "C:\\Users\\maria\\Downloads\\GPAce-main\\js\\semester-management.js", "source_location": "L1330"}, {"caller_nid": "js_semester_management_updatestorageusage", "callee": "getElementById", "is_member_call": true, "source_file": "C:\\Users\\maria\\Downloads\\GPAce-main\\js\\semester-management.js", "source_location": "L1331"}, {"caller_nid": "js_semester_management_updatestorageusage", "callee": "key", "is_member_call": true, "source_file": "C:\\Users\\maria\\Downloads\\GPAce-main\\js\\semester-management.js", "source_location": "L1338"}, {"caller_nid": "js_semester_management_updatestorageusage", "callee": "get", "is_member_call": true, "source_file": "C:\\Users\\maria\\Downloads\\GPAce-main\\js\\semester-management.js", "source_location": "L1339"}, {"caller_nid": "js_semester_management_updatestorageusage", "callee": "toFixed", "is_member_call": true, "source_file": "C:\\Users\\maria\\Downloads\\GPAce-main\\js\\semester-management.js", "source_location": "L1348"}, {"caller_nid": "js_semester_management_updatestorageusage", "callee": "toFixed", "is_member_call": true, "source_file": "C:\\Users\\maria\\Downloads\\GPAce-main\\js\\semester-management.js", "source_location": "L1350"}, {"caller_nid": "js_semester_management_updatestorageusage", "callee": "min", "is_member_call": true, "source_file": "C:\\Users\\maria\\Downloads\\GPAce-main\\js\\semester-management.js", "source_location": "L1356"}, {"caller_nid": "js_semester_management_updatestorageusage", "callee": "setAttribute", "is_member_call": true, "source_file": "C:\\Users\\maria\\Downloads\\GPAce-main\\js\\semester-management.js", "source_location": "L1359"}, {"caller_nid": "js_semester_management_updatestorageusage", "callee": "remove", "is_member_call": true, "source_file": "C:\\Users\\maria\\Downloads\\GPAce-main\\js\\semester-management.js", "source_location": "L1363"}, {"caller_nid": "js_semester_management_updatestorageusage", "callee": "add", "is_member_call": true, "source_file": "C:\\Users\\maria\\Downloads\\GPAce-main\\js\\semester-management.js", "source_location": "L1364"}, {"caller_nid": "js_semester_management_updatestorageusage", "callee": "remove", "is_member_call": true, "source_file": "C:\\Users\\maria\\Downloads\\GPAce-main\\js\\semester-management.js", "source_location": "L1366"}, {"caller_nid": "js_semester_management_updatestorageusage", "callee": "add", "is_member_call": true, "source_file": "C:\\Users\\maria\\Downloads\\GPAce-main\\js\\semester-management.js", "source_location": "L1367"}, {"caller_nid": "js_semester_management_updatestorageusage", "callee": "remove", "is_member_call": true, "source_file": "C:\\Users\\maria\\Downloads\\GPAce-main\\js\\semester-management.js", "source_location": "L1369"}, {"caller_nid": "js_semester_management_updatestorageusage", "callee": "add", "is_member_call": true, "source_file": "C:\\Users\\maria\\Downloads\\GPAce-main\\js\\semester-management.js", "source_location": "L1370"}, {"caller_nid": "js_semester_management_updatestorageusage", "callee": "error", "is_member_call": true, "source_file": "C:\\Users\\maria\\Downloads\\GPAce-main\\js\\semester-management.js", "source_location": "L1377"}, {"caller_nid": "js_semester_management_updatestorageusage", "callee": "getElementById", "is_member_call": true, "source_file": "C:\\Users\\maria\\Downloads\\GPAce-main\\js\\semester-management.js", "source_location": "L1378"}, {"caller_nid": "js_semester_management_showstoragemanager", "callee": "info", "is_member_call": true, "source_file": "C:\\Users\\maria\\Downloads\\GPAce-main\\js\\semester-management.js", "source_location": "L1389"}]}