{"nodes": [{"id": "c_users_maria_downloads_gpace_main_js_tweaks_panel_jsx", "label": "tweaks-panel.jsx", "file_type": "code", "source_file": "C:\\Users\\maria\\Downloads\\GPAce-main\\js\\tweaks-panel.jsx", "source_location": "L1"}, {"id": "js_tweaks_panel_settweak", "label": "setTweak()", "file_type": "code", "source_file": "C:\\Users\\maria\\Downloads\\GPAce-main\\js\\tweaks-panel.jsx", "source_location": "L13"}], "edges": [{"source": "c_users_maria_downloads_gpace_main_js_tweaks_panel_jsx", "target": "js_tweaks_panel_settweak", "relation": "contains", "confidence": "EXTRACTED", "source_file": "C:\\Users\\maria\\Downloads\\GPAce-main\\js\\tweaks-panel.jsx", "source_location": "L13", "weight": 1.0}], "raw_calls": [{"caller_nid": "js_tweaks_panel_settweak", "callee": "setTweaks", "is_member_call": false, "source_file": "C:\\Users\\maria\\Downloads\\GPAce-main\\js\\tweaks-panel.jsx", "source_location": "L14"}]}