{"nodes":[{"id":"storageservice_storageService","label":"Storage Service","file_type":"code","source_file":"js/services/StorageService.js"},{"id":"calendarservice_calendarService","label":"Calendar Service","file_type":"code","source_file":"js/services/CalendarService.js"},{"id":"gpaservice_gpaService","label":"GPA Service","file_type":"code","source_file":"js/services/GPAService.js"},{"id":"geminiservice_geminiService","label":"Gemini AI Service","file_type":"code","source_file":"js/services/GeminiService.js"},{"id":"mathservice_mathService","label":"Math Rendering Service","file_type":"code","source_file":"js/services/MathService.js"},{"id":"googledriveservice_googleDriveService","label":"Google Drive Service","file_type":"code","source_file":"js/services/GoogleDriveService.js"},{"id":"grindcontroller_grindController","label":"Grind Page Controller","file_type":"code","source_file":"js/controllers/GrindController.js"},{"id":"taskscontroller_tasksController","label":"Unified Tasks Controller","file_type":"code","source_file":"js/controllers/TasksController.js"},{"id":"relaxedcontroller_relaxedController","label":"Relaxed Mode Controller","file_type":"code","source_file":"js/controllers/RelaxedController.js"},{"id":"researchercontroller_researcherController","label":"AI Researcher Controller","file_type":"code","source_file":"js/controllers/ResearcherController.js"},{"id":"tasksystem_taskSystem","label":"Unified Task System","file_type":"code","source_file":"js/core/TaskSystem.js"},{"id":"tasksystemloader_TaskSystemLoader","label":"Task System Loader","file_type":"code","source_file":"js/core/TaskSystemLoader.js"},{"id":"sidedrawer_SideDrawer","label":"Settings Side Drawer","file_type":"code","source_file":"js/sideDrawer.js"},{"id":"calendarmanager_CalendarManager","label":"Calendar Orchestrator","file_type":"code","source_file":"js/calendarManager.js"},{"id":"gpapredictor_GPAPredictor","label":"GPA Predictor UI","file_type":"code","source_file":"js/gpa-predictor.js"},{"id":"relaxedmode_script_Facade","label":"Relaxed Mode View Facade","file_type":"code","source_file":"relaxed-mode/script.js"},{"id":"auth_Auth","label":"Centralized Authentication","file_type":"code","source_file":"js/auth.js"},{"id":"secretmanager_secretManager","label":"API Secret Manager","file_type":"code","source_file":"js/config/SecretManager.js"}],"edges":[{"source":"calendarservice_calendarService","target":"storageservice_storageService","relation":"references","confidence":"EXTRACTED","confidence_score":1.0,"source_file":"js/services/CalendarService.js"},{"source":"gpaservice_gpaService","target":"storageservice_storageService","relation":"references","confidence":"EXTRACTED","confidence_score":1.0,"source_file":"js/services/GPAService.js"},{"source":"geminiservice_geminiService","target":"secretmanager_secretManager","relation":"calls","confidence":"EXTRACTED","confidence_score":1.0,"source_file":"js/services/GeminiService.js"},{"source":"googledriveservice_googleDriveService","target":"secretmanager_secretManager","relation":"calls","confidence":"EXTRACTED","confidence_score":1.0,"source_file":"js/services/GoogleDriveService.js"},{"source":"googledriveservice_googleDriveService","target":"storageservice_storageService","relation":"references","confidence":"EXTRACTED","confidence_score":1.0,"source_file":"js/services/GoogleDriveService.js"},{"source":"grindcontroller_grindController","target":"tasksystem_taskSystem","relation":"orchestrates","confidence":"EXTRACTED","confidence_score":1.0,"source_file":"js/controllers/GrindController.js"},{"source":"taskscontroller_tasksController","target":"tasksystem_taskSystem","relation":"orchestrates","confidence":"EXTRACTED","confidence_score":1.0,"source_file":"js/controllers/TasksController.js"},{"source":"relaxedcontroller_relaxedController","target":"tasksystem_taskSystem","relation":"orchestrates","confidence":"EXTRACTED","confidence_score":1.0,"source_file":"js/controllers/RelaxedController.js"},{"source":"researchercontroller_researcherController","target":"geminiservice_geminiService","relation":"calls","confidence":"EXTRACTED","confidence_score":1.0,"source_file":"js/controllers/ResearcherController.js"},{"source":"researchercontroller_researcherController","target":"storageservice_storageService","relation":"references","confidence":"EXTRACTED","confidence_score":1.0,"source_file":"js/controllers/ResearcherController.js"},{"source":"tasksystem_taskSystem","target":"storageservice_storageService","relation":"references","confidence":"EXTRACTED","confidence_score":1.0,"source_file":"js/core/TaskSystem.js"},{"source":"tasksystem_taskSystem","target":"auth_Auth","relation":"references","confidence":"EXTRACTED","confidence_score":1.0,"source_file":"js/core/TaskSystem.js"},{"source":"tasksystemloader_TaskSystemLoader","target":"tasksystem_taskSystem","relation":"orchestrates","confidence":"EXTRACTED","confidence_score":1.0,"source_file":"js/core/TaskSystemLoader.js"},{"source":"sidedrawer_SideDrawer","target":"storageservice_storageService","relation":"references","confidence":"EXTRACTED","confidence_score":1.0,"source_file":"js/sideDrawer.js"},{"source":"sidedrawer_SideDrawer","target":"auth_Auth","relation":"references","confidence":"EXTRACTED","confidence_score":1.0,"source_file":"js/sideDrawer.js"},{"source":"calendarmanager_CalendarManager","target":"calendarservice_calendarService","relation":"orchestrates","confidence":"EXTRACTED","confidence_score":1.0,"source_file":"js/calendarManager.js"},{"source":"gpapredictor_GPAPredictor","target":"gpaservice_gpaService","relation":"orchestrates","confidence":"EXTRACTED","confidence_score":1.0,"source_file":"js/gpa-predictor.js"},{"source":"relaxedmode_script_Facade","target":"relaxedcontroller_relaxedController","relation":"calls","confidence":"EXTRACTED","confidence_score":1.0,"source_file":"relaxed-mode/script.js"}],"hyperedges":[],"input_tokens":0,"output_tokens":0}
